Workbook

Sheet README
A1: Newco Holdings Ltd (NEWC) — IPO pricing model
A3: Built | B3: 2026-10-17
A4: Currency | B4: USD
A5: Units | B5: millions
A6: Fiscal year end | B6: 31 December
A7: Generated by | B7: Financopedia build_model.py
A9: Colour key | B9: Blue = input you can change · Black = formula · Amber italic = estimated input
A10: Structure | B10: Every figure outside INPUTS and HISTORICALS is a formula. Change an input, the model moves.
A11: CHECKS tab | B11: Live assertions recomputing the model's identities. All must read PASS.
A12: History | B12: 10 reported years
A13: Pricing | B13: A weighted blend of three peer methods on NTM figures, then an IPO discount
A14: Primary vs secondary | B14: Primary shares raise money for the company; secondary shares transfer ownership and raise nothing for it
A15: Greenshoe | B15: Shown at full exercise; it is an option, not a certainty
... A18: Not advice | B18: Not financial advice and not produced by a licensed advisor. Assumptions are estimates and will be wrong to some degree; the sensitivity tab exists to show by how much.

Sheet INPUTS
A1: INPUTS — offering terms, peer set and the valuation blend
A2: The IPO discount is the most judgemental number here, which is why it is an axis of the sensitivity grid.
A3: Assumption | B3: Value | C3: Unit | E3: Basis / source
A4: IPO discount to peers | B4: 0.12 | C4: % | E4: ESTIMATE: 10-15% is the customary IPO discount; midpoint taken
A5: Primary gross proceeds target | B5: 900 | C5: millions | E5: Primary raise stated in the draft prospectus
A6: Secondary shares sold | B6: 60 | C6: shares | E6: Selling shareholder shares per the draft prospectus
A7: Pre-IPO shares outstanding | B7: 400 | C7: shares | E7: Share capital per the FY2025 audited accounts
A8: Underwriting fee | B8: 0.035 | C8: % | E8: Gross spread in the underwriting agreement
A9: Other offering costs | B9: 25 | C9: millions | E9: Listing, legal and audit costs per the prospectus
A10: Greenshoe (% of base offer) | B10: 0.15 | C10: % | E10: Over-allotment option in the underwriting agreement
A11: Net debt before the offering | B11: 1150 | C11: millions | E11: Total debt less cash, FY2025 balance sheet
A12: Marketing range (+/-) | B12: 0.075 | C12: % | E12: Marketing range width per the bookrunners' proposal
A13: Weight: EV/EBITDA method | B13: 0.5 | C13: % | E13: Primary method for this sector
A14: Weight: EV/Sales method | B14: 0.2 | C14: % | E14: Secondary check; least weight given margin dispersion
A15: Weight: P/E method | B15: 0.3 | C15: % | E15: Relevant because the company is already profitable
A16: Sensitivity: peer multiple step | B16: 0.5 | C16: x
A17: Sensitivity: IPO discount step | B17: 0.03 | C17: %
A19: Forecast driver | B19: Y1 | C19: Y2 | D19: Y3 | E19: Basis / source
A20: Revenue growth | B20: 0.075 | C20: 0.068 | D20: 0.06 | E20: Prospectus forecast, cross-checked against the 10-year CAGR
A21: EBITDA margin | B21: 0.262 | C21: 0.264 | D21: 0.265 | E21: ESTIMATE: held near FY2025, inside the 10-year range
A22: Net margin | B22: 0.15 | C22: 0.152 | D22: 0.154 | E22: ESTIMATE: FY2025 net margin carried forward
A24: Peer | B24: EV/EBITDA | C24: EV/Sales | D24: P/E | E24: Source
A25: Peer One | B25: 10.5 | C25: 2.6 | D25: 18 | E25: exchange data, 2026-10-16
A26: Peer Two | B26: 12 | C26: 3.1 | D26: 21.5 | E26: exchange data, 2026-10-16
A27: Peer Three | B27: 9.4 | C27: 2.2 | D27: 16.2 | E27: exchange data, 2026-10-16
A28: Peer Four | B28: 11.2 | C28: 2.9 | D28: 19.4 | E28: exchange data, 2026-10-16

Sheet HISTORICALS
A1: HISTORICALS — 10 reported years
A2: A long record is what distinguishes a pricing argument from a pitch; the last year drives the NTM figures the offer is priced on.
A3: Metric | B3: 2016 | C3: 2017 | D3: 2018 | E3: 2019 | F3: 2020 | G3: 2021 | H3: 2022 | I3: 2023 | J3: 2024 | K3: 2025 | L3: Source (filing, date)
A4: Revenue | B4: 2150 | C4: 2365 | D4: 2580 | E4: 2790 | F4: 2510 | G4: 2980 | H4: 3320 | I4: 3610 | J4: 3940 | K4: 4280 | L4: FY2016-FY2025 audited accounts in the draft prospectus, dated 2026-09-30 (revenue)
A5: EBITDA | B5: 473.1 | C5: 536.9 | D5: 596 | E5: 655.6 | F5: 479.4 | G5: 727.1 | H5: 830 | I5: 920.6 | J5: 1020.5 | K5: 1129.9 | L5: FY2016-FY2025 audited accounts in the draft prospectus, dated 2026-09-30 (ebitda)
A6: Net income | B6: 257.4 | C6: 294.7 | D6: 328.7 | E6: 363.2 | F6: 249.5 | G6: 406.8 | H6: 467.1 | I6: 520.6 | J6: 579.2 | K6: 644.1 | L6: FY2016-FY2025 audited accounts in the draft prospectus, dated 2026-09-30 (net_income)
A7: EBITDA margin | B7: =B5/B4 | C7: =C5/C4 | D7: =D5/D4 | E7: =E5/E4 | F7: =F5/F4 | G7: =G5/G4 | H7: =H5/H4 | I7: =I5/I4 | ... K7: =K5/K4
A9: What 10 years of history says
A10: Revenue CAGR over the period | B10: =((K4/B4)^(1/9))-1 | C10: Investors price growth off the record, not the forecast
A11: EBITDA margin — average | B11: =AVERAGE(B7:K7)

Sheet VALUATION
A1: VALUATION — three peer methods, blended, then discounted
A2: The blend weights are inputs, so the argument is visible rather than buried in one multiple.
A3: Item | B3: Value
A4: NTM revenue | B4: =HISTORICALS!K4*(1+INPUTS!B20)
A5: NTM EBITDA | B5: =B4*INPUTS!B21
A6: NTM net income | B6: =B4*INPUTS!B22
A8: Peer median EV/EBITDA | B8: =MEDIAN(INPUTS!B25:B28)
A9: Peer median EV/Sales | B9: =MEDIAN(INPUTS!C25:C28)
A10: Peer median P/E | B10: =MEDIAN(INPUTS!D25:D28)
A12: Equity value — EV/EBITDA method | B12: =B8*B5-INPUTS!$B$11
A13: Equity value — EV/Sales method | B13: =B9*B4-INPUTS!$B$11
A14: Equity value — P/E method | B14: =B10*B6 | C14: The P/E method needs no net debt adjustment — earnings are already after interest
A16: Blended equity value (weighted) | B16: =INPUTS!$B$13*B12+INPUTS!$B$14*B13+INPUTS!$B$15*B14
A17: Less: IPO discount | B17: =INPUTS!$B$4
A18: Pre-money equity value | B18: =B16*(1-B17)

Sheet OFFERING
A1: OFFERING — price, shares, ownership
A2: Primary shares are solved from the proceeds target at the offer price, so the post-money value per share equals the offer price.
A3: Item | B3: Value
A4: Offer price | B4: =VALUATION!B18/INPUTS!$B$7
A5: Marketing range — low | B5: =B4*(1-INPUTS!$B$12)
A6: Marketing range — high | B6: =B4*(1+INPUTS!$B$12)
A8: Pre-IPO shares | B8: =INPUTS!$B$7
A9: New (primary) shares issued | B9: =INPUTS!$B$5/B4
A10: Secondary shares sold | B10: =INPUTS!$B$6
A11: Base shares offered | B11: =B9+B10
A12: Greenshoe shares | B12: =B11*INPUTS!$B$10
A13: Post-IPO shares outstanding | B13: =B8+B9
A15: Pre-money equity value | B15: =VALUATION!B18
A16: Post-money equity value | B16: =B15+INPUTS!$B$5
A17: Free float (base offer) | B17: =B11/B13
A18: Free float (with greenshoe) | B18: =(B11+B12)/B13
A19: Dilution to existing holders | B19: =B9/B13
A21: Net debt after the offering | B21: =INPUTS!$B$11-PROCEEDS!B9
A22: Post-IPO enterprise value | B22: =B16+B21
A23: Implied EV/EBITDA at the offer | B23: =B22/VALUATION!B5
A24: Implied P/E at the offer | B24: =B16/VALUATION!B6
A25: Implied discount to peer EV/EBITDA | B25: =B23/VALUATION!B8-1 | C25: Where the offering actually prices against the peer set, after the cash raised changes net debt

Sheet PROCEEDS
A1: PROCEEDS — what is raised, what it costs, where it goes
A2: Secondary proceeds go to the selling shareholders, not the company. Only net primary proceeds fund anything below.
A3: Item | B3: Amount
A4: Gross primary proceeds | B4: =INPUTS!$B$5
A5: Gross secondary proceeds | B5: =INPUTS!$B$6*OFFERING!B4
A6: Total gross proceeds | B6: =B4+B5
A7: Underwriting fees | B7: =B6*INPUTS!$B$8
A8: Other offering costs | B8: =INPUTS!$B$9
A9: Net primary proceeds to the company | B9: =B4*(1-INPUTS!$B$8)-B8
A10: Net secondary proceeds to selling holders | B10: =B5*(1-INPUTS!$B$8)
A11: Greenshoe proceeds (if exercised in full) | B11: =OFFERING!B12*OFFERING!B4
A13: Use of proceeds (company's net primary only) | C13: Basis / source
A14: Repayment of term debt | B14: 463.9 | C14: Prospectus use of proceeds, section 4.2
A15: Capacity expansion | B15: 253 | C15: Prospectus use of proceeds, section 4.2
A16: General corporate purposes | B16: 126.6 | C16: Prospectus use of proceeds, section 4.2
A17: Total stated uses | B17: =SUM(B14:B16)
A18: Unallocated (net primary − stated uses) | B18: =B9-B17 | C18: A large unallocated balance is a finding, not an error — say so rather than inventing a purpose for it

Sheet SENSITIVITY
A1: SENSITIVITY — offer price: peer EV/EBITDA vs IPO discount
A2: Only the EV/EBITDA leg of the blend moves with the x-axis; the other two methods hold, which is what a real re-mark looks like.
B3: Peer EV/EBITDA ↓ / IPO discount →
C4: =INPUTS!$B$4+(COLUMN(C4)-5)*INPUTS!$B$17 | D4: =INPUTS!$B$4+(COLUMN(D4)-5)*INPUTS!$B$17 | E4: =INPUTS!$B$4+(COLUMN(E4)-5)*INPUTS!$B$17 | F4: =INPUTS!$B$4+(COLUMN(F4)-5)*INPUTS!$B$17 | G4: =INPUTS!$B$4+(COLUMN(G4)-5)*INPUTS!$B$17
B5: =VALUATION!$B$8+(ROW(B5)-7)*INPUTS!$B$16 | C5: =IF((INPUTS!$B$13*($B5*VALUATION!$B$5-INPUTS!$B$11)+INPUTS!$B$14*VALUATION!$B$13+INPUTS!$B$15*VALUATION!$B$14)<=0,NA(),(INPUTS!$B$13*($B5*VALUATION!$B$5-INPUTS!$B$11)+INPUTS!$B$14*VALUATION!$B$13+INPUTS!$B$15*VALUATION!$B$14)*(1-C$4)/INPUTS!$B$7) | D5: =IF((INPUTS!$B$13*($B5*VALUATION!$B$5-INPUTS!$B$11)+INPUTS!$B$14*VALUATION!$B$13+INPUTS!$B$15*VALUATION!$B$14)<=0,NA(),(INPUTS!$B$13*($B5*VALUATION!$B$5-INPUTS!$B$11)+INPUTS!$B$14*VALUATION!$B$13+INPUTS!$B$15*VALUATION!$B$14)*(1-D$4)/INPUTS!$B$7) | E5: =IF((INPUTS!$B$13*($B5*VALUATION!$B$5-INPUTS!$B$11)+INPUTS!$B$14*VALUATION!$B$13+INPUTS!$B$15*VALUATION!$B$14)<=0,NA(),(INPUTS!$B$13*($B5*VALUATION!$B$5-INPUTS!$B$11)+INPUTS!$B$14*VALUATION!$B$13+INPUTS!$B$15*VALUATION!$B$14)*(1-E$4)/INPUTS!$B$7) | F5: =IF((INPUTS!$B$13*($B5*VALUATION!$B$5-INPUTS!$B$11)+INPUTS!$B$14*VALUATION!$B$13+INPUTS!$B$15*VALUATION!$B$14)<=0,NA(),(INPUTS!$B$13*($B5*VALUATION!$B$5-INPUTS!$B$11)+INPUTS!$B$14*VALUATION!$B$13+INPUTS!$B$15*VALUATION!$B$14)*(1-F$4)/INPUTS!$B$7) | G5: =IF((INPUTS!$B$13*($B5*VALUATION!$B$5-INPUTS!$B$11)+INPUTS!$B$14*VALUATION!$B$13+INPUTS!$B$15*VALUATION!$B$14)<=0,NA(),(INPUTS!$B$13*($B5*VALUATION!$B$5-INPUTS!$B$11)+INPUTS!$B$14*VALUATION!$B$13+INPUTS!$B$15*VALUATION!$B$14)*(1-G$4)/INPUTS!$B$7)
B6: =VALUATION!$B$8+(ROW(B6)-7)*INPUTS!$B$16 | C6: =IF((INPUTS!$B$13*($B6*VALUATION!$B$5-INPUTS!$B$11)+INPUTS!$B$14*VALUATION!$B$13+INPUTS!$B$15*VALUATION!$B$14)<=0,NA(),(INPUTS!$B$13*($B6*VALUATION!$B$5-INPUTS!$B$11)+INPUTS!$B$14*VALUATION!$B$13+INPUTS!$B$15*VALUATION!$B$14)*(1-C$4)/INPUTS!$B$7) | D6: =IF((INPUTS!$B$13*($B6*VALUATION!$B$5-INPUTS!$B$11)+INPUTS!$B$14*VALUATION!$B$13+INPUTS!$B$15*VALUATION!$B$14)<=0,NA(),(INPUTS!$B$13*($B6*VALUATION!$B$5-INPUTS!$B$11)+INPUTS!$B$14*VALUATION!$B$13+INPUTS!$B$15*VALUATION!$B$14)*(1-D$4)/INPUTS!$B$7) | E6: =IF((INPUTS!$B$13*($B6*VALUATION!$B$5-INPUTS!$B$11)+INPUTS!$B$14*VALUATION!$B$13+INPUTS!$B$15*VALUATION!$B$14)<=0,NA(),(INPUTS!$B$13*($B6*VALUATION!$B$5-INPUTS!$B$11)+INPUTS!$B$14*VALUATION!$B$13+INPUTS!$B$15*VALUATION!$B$14)*(1-E$4)/INPUTS!$B$7) | F6: =IF((INPUTS!$B$13*($B6*VALUATION!$B$5-INPUTS!$B$11)+INPUTS!$B$14*VALUATION!$B$13+INPUTS!$B$15*VALUATION!$B$14)<=0,NA(),(INPUTS!$B$13*($B6*VALUATION!$B$5-INPUTS!$B$11)+INPUTS!$B$14*VALUATION!$B$13+INPUTS!$B$15*VALUATION!$B$14)*(1-F$4)/INPUTS!$B$7) | G6: =IF((INPUTS!$B$13*($B6*VALUATION!$B$5-INPUTS!$B$11)+INPUTS!$B$14*VALUATION!$B$13+INPUTS!$B$15*VALUATION!$B$14)<=0,NA(),(INPUTS!$B$13*($B6*VALUATION!$B$5-INPUTS!$B$11)+INPUTS!$B$14*VALUATION!$B$13+INPUTS!$B$15*VALUATION!$B$14)*(1-G$4)/INPUTS!$B$7)
B7: =VALUATION!$B$8+(ROW(B7)-7)*INPUTS!$B$16 | C7: =IF((INPUTS!$B$13*($B7*VALUATION!$B$5-INPUTS!$B$11)+INPUTS!$B$14*VALUATION!$B$13+INPUTS!$B$15*VALUATION!$B$14)<=0,NA(),(INPUTS!$B$13*($B7*VALUATION!$B$5-INPUTS!$B$11)+INPUTS!$B$14*VALUATION!$B$13+INPUTS!$B$15*VALUATION!$B$14)*(1-C$4)/INPUTS!$B$7) | D7: =IF((INPUTS!$B$13*($B7*VALUATION!$B$5-INPUTS!$B$11)+INPUTS!$B$14*VALUATION!$B$13+INPUTS!$B$15*VALUATION!$B$14)<=0,NA(),(INPUTS!$B$13*($B7*VALUATION!$B$5-INPUTS!$B$11)+INPUTS!$B$14*VALUATION!$B$13+INPUTS!$B$15*VALUATION!$B$14)*(1-D$4)/INPUTS!$B$7) | E7: =IF((INPUTS!$B$13*($B7*VALUATION!$B$5-INPUTS!$B$11)+INPUTS!$B$14*VALUATION!$B$13+INPUTS!$B$15*VALUATION!$B$14)<=0,NA(),(INPUTS!$B$13*($B7*VALUATION!$B$5-INPUTS!$B$11)+INPUTS!$B$14*VALUATION!$B$13+INPUTS!$B$15*VALUATION!$B$14)*(1-E$4)/INPUTS!$B$7) | F7: =IF((INPUTS!$B$13*($B7*VALUATION!$B$5-INPUTS!$B$11)+INPUTS!$B$14*VALUATION!$B$13+INPUTS!$B$15*VALUATION!$B$14)<=0,NA(),(INPUTS!$B$13*($B7*VALUATION!$B$5-INPUTS!$B$11)+INPUTS!$B$14*VALUATION!$B$13+INPUTS!$B$15*VALUATION!$B$14)*(1-F$4)/INPUTS!$B$7) | G7: =IF((INPUTS!$B$13*($B7*VALUATION!$B$5-INPUTS!$B$11)+INPUTS!$B$14*VALUATION!$B$13+INPUTS!$B$15*VALUATION!$B$14)<=0,NA(),(INPUTS!$B$13*($B7*VALUATION!$B$5-INPUTS!$B$11)+INPUTS!$B$14*VALUATION!$B$13+INPUTS!$B$15*VALUATION!$B$14)*(1-G$4)/INPUTS!$B$7)
B8: =VALUATION!$B$8+(ROW(B8)-7)*INPUTS!$B$16 | C8: =IF((INPUTS!$B$13*($B8*VALUATION!$B$5-INPUTS!$B$11)+INPUTS!$B$14*VALUATION!$B$13+INPUTS!$B$15*VALUATION!$B$14)<=0,NA(),(INPUTS!$B$13*($B8*VALUATION!$B$5-INPUTS!$B$11)+INPUTS!$B$14*VALUATION!$B$13+INPUTS!$B$15*VALUATION!$B$14)*(1-C$4)/INPUTS!$B$7) | D8: =IF((INPUTS!$B$13*($B8*VALUATION!$B$5-INPUTS!$B$11)+INPUTS!$B$14*VALUATION!$B$13+INPUTS!$B$15*VALUATION!$B$14)<=0,NA(),(INPUTS!$B$13*($B8*VALUATION!$B$5-INPUTS!$B$11)+INPUTS!$B$14*VALUATION!$B$13+INPUTS!$B$15*VALUATION!$B$14)*(1-D$4)/INPUTS!$B$7) | E8: =IF((INPUTS!$B$13*($B8*VALUATION!$B$5-INPUTS!$B$11)+INPUTS!$B$14*VALUATION!$B$13+INPUTS!$B$15*VALUATION!$B$14)<=0,NA(),(INPUTS!$B$13*($B8*VALUATION!$B$5-INPUTS!$B$11)+INPUTS!$B$14*VALUATION!$B$13+INPUTS!$B$15*VALUATION!$B$14)*(1-E$4)/INPUTS!$B$7) | F8: =IF((INPUTS!$B$13*($B8*VALUATION!$B$5-INPUTS!$B$11)+INPUTS!$B$14*VALUATION!$B$13+INPUTS!$B$15*VALUATION!$B$14)<=0,NA(),(INPUTS!$B$13*($B8*VALUATION!$B$5-INPUTS!$B$11)+INPUTS!$B$14*VALUATION!$B$13+INPUTS!$B$15*VALUATION!$B$14)*(1-F$4)/INPUTS!$B$7) | G8: =IF((INPUTS!$B$13*($B8*VALUATION!$B$5-INPUTS!$B$11)+INPUTS!$B$14*VALUATION!$B$13+INPUTS!$B$15*VALUATION!$B$14)<=0,NA(),(INPUTS!$B$13*($B8*VALUATION!$B$5-INPUTS!$B$11)+INPUTS!$B$14*VALUATION!$B$13+INPUTS!$B$15*VALUATION!$B$14)*(1-G$4)/INPUTS!$B$7)
B9: =VALUATION!$B$8+(ROW(B9)-7)*INPUTS!$B$16 | C9: =IF((INPUTS!$B$13*($B9*VALUATION!$B$5-INPUTS!$B$11)+INPUTS!$B$14*VALUATION!$B$13+INPUTS!$B$15*VALUATION!$B$14)<=0,NA(),(INPUTS!$B$13*($B9*VALUATION!$B$5-INPUTS!$B$11)+INPUTS!$B$14*VALUATION!$B$13+INPUTS!$B$15*VALUATION!$B$14)*(1-C$4)/INPUTS!$B$7) | D9: =IF((INPUTS!$B$13*($B9*VALUATION!$B$5-INPUTS!$B$11)+INPUTS!$B$14*VALUATION!$B$13+INPUTS!$B$15*VALUATION!$B$14)<=0,NA(),(INPUTS!$B$13*($B9*VALUATION!$B$5-INPUTS!$B$11)+INPUTS!$B$14*VALUATION!$B$13+INPUTS!$B$15*VALUATION!$B$14)*(1-D$4)/INPUTS!$B$7) | E9: =IF((INPUTS!$B$13*($B9*VALUATION!$B$5-INPUTS!$B$11)+INPUTS!$B$14*VALUATION!$B$13+INPUTS!$B$15*VALUATION!$B$14)<=0,NA(),(INPUTS!$B$13*($B9*VALUATION!$B$5-INPUTS!$B$11)+INPUTS!$B$14*VALUATION!$B$13+INPUTS!$B$15*VALUATION!$B$14)*(1-E$4)/INPUTS!$B$7) | F9: =IF((INPUTS!$B$13*($B9*VALUATION!$B$5-INPUTS!$B$11)+INPUTS!$B$14*VALUATION!$B$13+INPUTS!$B$15*VALUATION!$B$14)<=0,NA(),(INPUTS!$B$13*($B9*VALUATION!$B$5-INPUTS!$B$11)+INPUTS!$B$14*VALUATION!$B$13+INPUTS!$B$15*VALUATION!$B$14)*(1-F$4)/INPUTS!$B$7) | G9: =IF((INPUTS!$B$13*($B9*VALUATION!$B$5-INPUTS!$B$11)+INPUTS!$B$14*VALUATION!$B$13+INPUTS!$B$15*VALUATION!$B$14)<=0,NA(),(INPUTS!$B$13*($B9*VALUATION!$B$5-INPUTS!$B$11)+INPUTS!$B$14*VALUATION!$B$13+INPUTS!$B$15*VALUATION!$B$14)*(1-G$4)/INPUTS!$B$7)
B11: Shaded centre cell = base case; it must equal the offer price on OFFERING (CHECKS verifies this).

Sheet CHECKS
A1: CHECKS — live assertions, recomputed by Excel
A2: Every row must read PASS. These recompute identities independently of the cells they test.
A3: Check | B3: Result | C3: What it proves
A4: Valuation weights sum to 100% | B4: =IF(ABS(INPUTS!$B$13+INPUTS!$B$14+INPUTS!$B$15-1)<0.0001,"PASS","FAIL") | C4: The blend is a weighted average, not an accident
A5: Post-money value per share equals the offer price | B5: =IF(ABS(OFFERING!B16/OFFERING!B13-OFFERING!B4)<0.0001,"PASS","FAIL") | C5: Primary shares were solved at the offer price, so the two must agree
A6: Primary shares raise exactly the proceeds target | B6: =IF(ABS(OFFERING!B9*OFFERING!B4-INPUTS!$B$5)<0.01,"PASS","FAIL") | C6: Shares issued x price = gross primary proceeds
A7: Pre-money plus proceeds equals post-money | B7: =IF(ABS(OFFERING!B16-(OFFERING!B15+INPUTS!$B$5))<0.01,"PASS","FAIL") | C7: No value appears or disappears at the moment of issue
A8: Offer price is positive | B8: =IF(OFFERING!B4>0,"PASS","FAIL") | C8: A non-positive price means the blend or the discount is wrong
A9: IPO discount between 0% and 100% | B9: =IF(AND(INPUTS!$B$4>=0,INPUTS!$B$4<1),"PASS","FAIL") | C9: A discount outside this range is a data error
A10: Free float does not exceed 100% | B10: =IF(OFFERING!B18<=1,"PASS","FAIL") | C10: Shares offered cannot exceed shares outstanding
A11: Net primary proceeds below gross | B11: =IF(PROCEEDS!B9<PROCEEDS!B4,"PASS","FAIL") | C11: Fees and costs are actually deducted
A12: Sensitivity centre equals the offer price | B12: =IF(ABS(SENSITIVITY!E7-OFFERING!B4)<0.0001,"PASS","FAIL") | C12: The grid is wired to the same valuation
A13: Implied multiple at or below the peer median | B13: =IF(OFFERING!B23<=VALUATION!B8,"PASS","REVIEW") | C13: An IPO pricing above its peer set is unusual enough to need saying
A14: Use of proceeds fully allocated | B14: =IF(ABS(PROCEEDS!B18)<0.01,"PASS","REVIEW") | C14: REVIEW means a balance is unallocated — report it, do not invent a use
A15: Free float at or above 15% | B15: =IF(OFFERING!B17>=0.15,"PASS","REVIEW") | C15: Most exchanges require a minimum float; below this, check the rule for the listing venue
A17: OVERALL | B17: =IF(COUNTIF(B4:B15,"FAIL")=0,"ALL PASS","FAILURES PRESENT")
