Workbook

Sheet README
A1: Testco Industries plc (TSTC) — LBO model
A3: Built | B3: 2026-10-17
A4: Currency | B4: USD
A5: Units | B5: millions
A6: Fiscal year end | B6: 31 December
A7: Generated by | B7: Financopedia build_model.py
A9: Colour key | B9: Blue = input you can change · Black = formula · Amber italic = estimated input
A10: Structure | B10: Every figure outside INPUTS and HISTORICALS is a formula. Change an input, the model moves.
A11: CHECKS tab | B11: Live assertions recomputing the model's identities. All must read PASS.
A12: History | B12: 10 reported years; the last is LTM and sizes both the debt and the entry price
A13: Hold | B13: 5 years to exit
A14: Debt sizing | B14: In turns of LTM EBITDA, so the structure does not move when the entry multiple does
A15: Interest | B15: Charged on opening balances — no iterative calculation
... A19: Not advice | B19: Not financial advice and not produced by a licensed advisor. Assumptions are estimates and will be wrong to some degree; the sensitivity tab exists to show by how much.

Sheet INPUTS
A1: INPUTS — deal terms, capital structure and operating case
A2: Debt is sized in turns of LTM EBITDA, so the structure does not move when the entry multiple does.
A3: Assumption | B3: Value | C3: Unit | G3: Basis / source
A4: Entry EV/EBITDA multiple | B4: 10.5 | C4: x | G4: Negotiated price per the draft SPA
A5: Exit EV/EBITDA multiple | B5: 10.5 | C5: x | G5: ESTIMATE: held flat to entry, the conservative convention
A6: Transaction fees (% of EV) | B6: 0.02 | C6: % | G6: Advisory fee schedule in the engagement letter
A7: Financing fees (% of new debt) | B7: 0.025 | C7: % | G7: OID and arrangement fees per the commitment papers
A8: Rollover equity | B8: 150 | C8: millions | G8: Management rollover agreed in the term sheet
A9: Tax rate | B9: 0.21 | C9: % | G9: FY2025 effective rate per the 10-K tax footnote
A10: Cash sweep (% of surplus) | B10: 0.75 | C10: % | G10: ESTIMATE: 75% sweep per the draft credit agreement
A11: Minimum cash balance | B11: 150 | C11: millions | G11: Minimum operating cash per management
A12: Cash left on the balance sheet at close | B12: 200 | C12: millions | G12: Cash funded to the balance sheet at close
A13: Interest earned on cash | B13: 0.03 | C13: % | G13: Short-term deposit rate, 2026-10-16
A14: Sensitivity: entry multiple step | B14: 0.5 | C14: x
A15: Sensitivity: exit multiple step | B15: 0.5 | C15: x
A17: Operating driver | B17: Y1 | C17: Y2 | D17: Y3 | E17: Y4 | F17: Y5 | G17: Basis / source
A18: Revenue growth | B18: 0.07 | C18: 0.062 | D18: 0.055 | E18: 0.048 | F18: 0.042 | G18: Management case presented in the CIM, cross-checked against the 10-year CAGR
A19: EBITDA margin | B19: 0.262 | C19: 0.264 | D19: 0.265 | E19: 0.266 | F19: 0.267 | G19: ESTIMATE: held near FY2025, inside the 10-year range
A20: D&A (% of revenue) | B20: 0.049 | C20: 0.049 | D20: 0.049 | E20: 0.049 | F20: 0.049 | G20: 10-year average
A21: Capex (% of revenue) | B21: 0.06 | C21: 0.059 | D21: 0.058 | E21: 0.057 | F21: 0.056 | G21: Y1 guided; fades to the 10-year average
A22: Working capital (% of revenue) | B22: 0.1 | C22: 0.1 | D22: 0.1 | E22: 0.1 | F22: 0.1 | G22: 10-year average working capital intensity
A24: Debt tranche (in priority order) | B24: Turns of EBITDA | C24: Rate | D24: Annual amortisation | E24: In the sweep? | F24: Basis / source
A25: Term Loan A | B25: 2 | C25: 0.065 | D25: 0.1 | E25: 1 | F25: Commitment papers: 2.0x LTM EBITDA, SOFR+275, 10% annual amortisation
A26: Term Loan B | B26: 2.5 | C26: 0.075 | D26: 0.01 | E26: 1 | F26: Commitment papers: 2.5x LTM EBITDA, SOFR+375, 1% annual amortisation
A27: Mezzanine | B27: 1 | C27: 0.11 | D27: 0 | E27: 0 | F27: Mezzanine term sheet: 1.0x LTM EBITDA, 11% cash pay, bullet

Sheet HISTORICALS
A1: HISTORICALS — 10 reported years
A2: The last column is LTM: it sizes the debt and prices the entry, so it carries more weight than any other figure here.
A3: Metric | B3: 2016 | C3: 2017 | D3: 2018 | E3: 2019 | F3: 2020 | G3: 2021 | H3: 2022 | I3: 2023 | J3: 2024 | K3: 2025 | L3: Source (filing, date)
A4: Revenue | B4: 2150 | C4: 2365 | D4: 2580 | E4: 2790 | F4: 2510 | G4: 2980 | H4: 3320 | I4: 3610 | J4: 3940 | K4: 4280 | L4: FY2016-FY2025 10-K filings; FY2025 filed 2026-02-14 (revenue)
A5: EBITDA | B5: 473.1 | C5: 536.9 | D5: 596 | E5: 655.6 | F5: 479.4 | G5: 727.1 | H5: 830 | I5: 920.6 | J5: 1020.5 | K5: 1129.9 | L5: FY2016-FY2025 10-K filings; FY2025 filed 2026-02-14 (ebitda)
A6: Capex | B6: 133.3 | C6: 153.7 | D6: 157.4 | E6: 161.8 | F6: 102.9 | G6: 175.8 | H6: 209.2 | I6: 216.6 | J6: 228.5 | K6: 256.8 | L6: FY2016-FY2025 10-K filings; FY2025 filed 2026-02-14 (capex)
A7: Net working capital (balance) | B7: 215 | C7: 236.5 | D7: 258 | E7: 279 | F7: 251 | G7: 298 | H7: 332 | I7: 361 | J7: 394 | K7: 428 | L7: FY2016-FY2025 10-K filings; FY2025 filed 2026-02-14 (nwc_balance)
A8: EBITDA margin | B8: =B5/B4 | C8: =C5/C4 | D8: =D5/D4 | E8: =E5/E4 | F8: =F5/F4 | G8: =G5/G4 | H8: =H5/H4 | I8: =I5/I4 | ... K8: =K5/K4
A10: What 10 years of history says
A11: Revenue CAGR over the period | B11: =((K4/B4)^(1/9))-1 | C11: A leveraged structure is paid down out of growth; compare with the case
A12: EBITDA margin — average | B12: =AVERAGE(B8:K8)
A13: EBITDA margin — worst year | B13: =MIN(B8:K8) | C13: Test the structure against this, not the average — covenants break in bad years

Sheet SOURCES_USES
A1: SOURCES AND USES — the entry
A2: Sponsor equity is the plug: it is whatever the uses are not funded by.
A3: Item | B3: Amount | C3: Turns of EBITDA
A4: LTM EBITDA | B4: =HISTORICALS!K5
A5: Entry multiple | B5: =INPUTS!$B$4
A6: Entry enterprise value | B6: =B4*B5
A8: SOURCES
A9: Term Loan A | B9: =INPUTS!B25*$B$4 | C9: =B9/$B$4
A10: Term Loan B | B10: =INPUTS!B26*$B$4 | C10: =B10/$B$4
A11: Mezzanine | B11: =INPUTS!B27*$B$4 | C11: =B11/$B$4
A12: Total new debt | B12: =SUM(B9:B11) | C12: =B12/$B$4
A13: Rollover equity | B13: =INPUTS!$B$8
A14: Sponsor equity (plug) | B14: =B22-B12-B13
A15: Total sources | B15: =B12+B13+B14
A17: USES
A18: Purchase of enterprise | B18: =B6
A19: Transaction fees | B19: =B6*INPUTS!$B$6
A20: Financing fees | B20: =B12*INPUTS!$B$7
A21: Cash to the balance sheet | B21: =INPUTS!$B$12
A22: Total uses | B22: =SUM(B18:B21)
A24: Check: sources − uses | B24: =B15-B22
A25: Net debt at close | B25: =B12-INPUTS!$B$12
A26: Entry equity value (EV − net debt) | B26: =B6-B25
A27: Opening leverage (net debt / EBITDA) | B27: =B25/B4

Sheet PROJECTION
A1: PROJECTION — the operating case under the new structure
A2: Interest comes from the DEBT tab and is charged on opening balances, so nothing here is circular.
A3: Metric | B3: 2026 | C3: 2027 | D3: 2028 | E3: 2029 | F3: 2030
A4: Revenue | B4: =HISTORICALS!$K$4*(1+INPUTS!B$18) | C4: =B4*(1+INPUTS!C$18) | D4: =C4*(1+INPUTS!D$18) | E4: =D4*(1+INPUTS!E$18) | F4: =E4*(1+INPUTS!F$18)
A5: EBITDA | B5: =B4*INPUTS!B$19 | C5: =C4*INPUTS!C$19 | D5: =D4*INPUTS!D$19 | E5: =E4*INPUTS!E$19 | F5: =F4*INPUTS!F$19
A6: D&A | B6: =B4*INPUTS!B$20 | C6: =C4*INPUTS!C$20 | D6: =D4*INPUTS!D$20 | E6: =E4*INPUTS!E$20 | F6: =F4*INPUTS!F$20
A7: EBIT | B7: =B5-B6 | C7: =C5-C6 | D7: =D5-D6 | E7: =E5-E6 | F7: =F5-F6
A8: Interest expense | B8: =DEBT!B27 | C8: =DEBT!C27 | D8: =DEBT!D27 | E8: =DEBT!E27 | F8: =DEBT!F27
A9: Interest income | B9: =DEBT!B28*INPUTS!$B$13 | C9: =DEBT!C28*INPUTS!$B$13 | D9: =DEBT!D28*INPUTS!$B$13 | E9: =DEBT!E28*INPUTS!$B$13 | F9: =DEBT!F28*INPUTS!$B$13
A10: Profit before tax | B10: =B7-B8+B9 | C10: =C7-C8+C9 | D10: =D7-D8+D9 | E10: =E7-E8+E9 | F10: =F7-F8+F9
A11: Tax | B11: =MAX(B10,0)*INPUTS!$B$9 | C11: =MAX(C10,0)*INPUTS!$B$9 | D11: =MAX(D10,0)*INPUTS!$B$9 | E11: =MAX(E10,0)*INPUTS!$B$9 | F11: =MAX(F10,0)*INPUTS!$B$9
A12: Net income | B12: =B10-B11 | C12: =C10-C11 | D12: =D10-D11 | E12: =E10-E11 | F12: =F10-F11
A13: Capex | B13: =B4*INPUTS!B$21 | C13: =C4*INPUTS!C$21 | D13: =D4*INPUTS!D$21 | E13: =E4*INPUTS!E$21 | F13: =F4*INPUTS!F$21
A14: Working capital (balance) | B14: =B4*INPUTS!B$22 | C14: =C4*INPUTS!C$22 | D14: =D4*INPUTS!D$22 | E14: =E4*INPUTS!E$22 | F14: =F4*INPUTS!F$22
A15: Change in working capital | B15: =B14-HISTORICALS!$K$7 | C15: =C14-B14 | D15: =D14-C14 | E15: =E14-D14 | F15: =F14-E14
A16: Free cash flow before debt service | B16: =B12+B6-B13-B15 | C16: =C12+C6-C13-C15 | D16: =D12+D6-D13-D15 | E16: =E12+E6-E13-E15 | F16: =F12+F6-F13-F15

Sheet DEBT
A1: DEBT SCHEDULE — mandatory amortisation then cash sweep
A2: Tranches are swept in the order listed. Each year's interest is charged on that year's opening balance.
A3: Line | B3: 2026 | C3: 2027 | D3: 2028 | E3: 2029 | F3: 2030
A4: Term Loan A
A5: Opening balance | B5: =SOURCES_USES!$B$9 | C5: =B8 | D5: =C8 | E5: =D8 | F5: =E8
A6: Mandatory amortisation | B6: =MIN(INPUTS!$D$25*SOURCES_USES!$B$9,B5) | C6: =MIN(INPUTS!$D$25*SOURCES_USES!$B$9,C5) | D6: =MIN(INPUTS!$D$25*SOURCES_USES!$B$9,D5) | E6: =MIN(INPUTS!$D$25*SOURCES_USES!$B$9,E5) | F6: =MIN(INPUTS!$D$25*SOURCES_USES!$B$9,F5)
A7: Cash sweep | B7: =INPUTS!$E$25*MIN(B5-B6,MAX(0,B31)) | C7: =INPUTS!$E$25*MIN(C5-C6,MAX(0,C31)) | D7: =INPUTS!$E$25*MIN(D5-D6,MAX(0,D31)) | E7: =INPUTS!$E$25*MIN(E5-E6,MAX(0,E31)) | F7: =INPUTS!$E$25*MIN(F5-F6,MAX(0,F31))
A8: Closing balance | B8: =B5-B6-B7 | C8: =C5-C6-C7 | D8: =D5-D6-D7 | E8: =E5-E6-E7 | F8: =F5-F6-F7
A9: Interest expense | B9: =B5*INPUTS!$C$25 | C9: =C5*INPUTS!$C$25 | D9: =D5*INPUTS!$C$25 | E9: =E5*INPUTS!$C$25 | F9: =F5*INPUTS!$C$25
A10: Term Loan B
A11: Opening balance | B11: =SOURCES_USES!$B$10 | C11: =B14 | D11: =C14 | E11: =D14 | F11: =E14
A12: Mandatory amortisation | B12: =MIN(INPUTS!$D$26*SOURCES_USES!$B$10,B11) | C12: =MIN(INPUTS!$D$26*SOURCES_USES!$B$10,C11) | D12: =MIN(INPUTS!$D$26*SOURCES_USES!$B$10,D11) | E12: =MIN(INPUTS!$D$26*SOURCES_USES!$B$10,E11) | F12: =MIN(INPUTS!$D$26*SOURCES_USES!$B$10,F11)
A13: Cash sweep | B13: =INPUTS!$E$26*MIN(B11-B12,MAX(0,B31-B7)) | C13: =INPUTS!$E$26*MIN(C11-C12,MAX(0,C31-C7)) | D13: =INPUTS!$E$26*MIN(D11-D12,MAX(0,D31-D7)) | E13: =INPUTS!$E$26*MIN(E11-E12,MAX(0,E31-E7)) | F13: =INPUTS!$E$26*MIN(F11-F12,MAX(0,F31-F7))
A14: Closing balance | B14: =B11-B12-B13 | C14: =C11-C12-C13 | D14: =D11-D12-D13 | E14: =E11-E12-E13 | F14: =F11-F12-F13
A15: Interest expense | B15: =B11*INPUTS!$C$26 | C15: =C11*INPUTS!$C$26 | D15: =D11*INPUTS!$C$26 | E15: =E11*INPUTS!$C$26 | F15: =F11*INPUTS!$C$26
A16: Mezzanine
A17: Opening balance | B17: =SOURCES_USES!$B$11 | C17: =B20 | D17: =C20 | E17: =D20 | F17: =E20
A18: Mandatory amortisation | B18: =MIN(INPUTS!$D$27*SOURCES_USES!$B$11,B17) | C18: =MIN(INPUTS!$D$27*SOURCES_USES!$B$11,C17) | D18: =MIN(INPUTS!$D$27*SOURCES_USES!$B$11,D17) | E18: =MIN(INPUTS!$D$27*SOURCES_USES!$B$11,E17) | F18: =MIN(INPUTS!$D$27*SOURCES_USES!$B$11,F17)
A19: Cash sweep | B19: =INPUTS!$E$27*MIN(B17-B18,MAX(0,B31-B7-B13)) | C19: =INPUTS!$E$27*MIN(C17-C18,MAX(0,C31-C7-C13)) | D19: =INPUTS!$E$27*MIN(D17-D18,MAX(0,D31-D7-D13)) | E19: =INPUTS!$E$27*MIN(E17-E18,MAX(0,E31-E7-E13)) | F19: =INPUTS!$E$27*MIN(F17-F18,MAX(0,F31-F7-F13))
A20: Closing balance | B20: =B17-B18-B19 | C20: =C17-C18-C19 | D20: =D17-D18-D19 | E20: =E17-E18-E19 | F20: =F17-F18-F19
A21: Interest expense | B21: =B17*INPUTS!$C$27 | C21: =C17*INPUTS!$C$27 | D21: =D17*INPUTS!$C$27 | E21: =E17*INPUTS!$C$27 | F21: =F17*INPUTS!$C$27
A23: Total opening debt | B23: =B5+B11+B17 | C23: =C5+C11+C17 | D23: =D5+D11+D17 | E23: =E5+E11+E17 | F23: =F5+F11+F17
A24: Total mandatory amortisation | B24: =B6+B12+B18 | C24: =C6+C12+C18 | D24: =D6+D12+D18 | E24: =E6+E12+E18 | F24: =F6+F12+F18
A25: Total cash sweep | B25: =B7+B13+B19 | C25: =C7+C13+C19 | D25: =D7+D13+D19 | E25: =E7+E13+E19 | F25: =F7+F13+F19
A26: Total closing debt | B26: =B8+B14+B20 | C26: =C8+C14+C20 | D26: =D8+D14+D20 | E26: =E8+E14+E20 | F26: =F8+F14+F20
A27: Total interest expense | B27: =B9+B15+B21 | C27: =C9+C15+C21 | D27: =D9+D15+D21 | E27: =E9+E15+E21 | F27: =F9+F15+F21
A28: Opening cash | B28: =INPUTS!$B$12 | C28: =B32 | D28: =C32 | E28: =D32 | F28: =E32
A29: Free cash flow before debt service | B29: =PROJECTION!B16 | C29: =PROJECTION!C16 | D29: =PROJECTION!D16 | E29: =PROJECTION!E16 | F29: =PROJECTION!F16
A30: Cash before sweep | B30: =B28+B29-B24 | C30: =C28+C29-C24 | D30: =D28+D29-D24 | E30: =E28+E29-E24 | F30: =F28+F29-F24
A31: Cash available for sweep | B31: =MAX(0,B30-INPUTS!$B$11)*INPUTS!$B$10 | C31: =MAX(0,C30-INPUTS!$B$11)*INPUTS!$B$10 | D31: =MAX(0,D30-INPUTS!$B$11)*INPUTS!$B$10 | E31: =MAX(0,E30-INPUTS!$B$11)*INPUTS!$B$10 | F31: =MAX(0,F30-INPUTS!$B$11)*INPUTS!$B$10
A32: Closing cash | B32: =B30-B25 | C32: =C30-C25 | D32: =D30-D25 | E32: =E30-E25 | F32: =F30-F25
A33: Net debt | B33: =B26-B32 | C33: =C26-C32 | D33: =D26-D32 | E33: =E26-E32 | F33: =F26-F32
A34: Net debt / EBITDA | B34: =B33/PROJECTION!B5 | C34: =C33/PROJECTION!C5 | D34: =D33/PROJECTION!D5 | E34: =E33/PROJECTION!E5 | F34: =F33/PROJECTION!F5

Sheet RETURNS
A1: RETURNS — exit and attribution
A2: Attribution is an identity, not an estimate: the three components sum exactly to the change in equity value.
A3: Item | B3: Value
A4: Exit-year EBITDA | B4: =PROJECTION!F5
A5: Exit multiple | B5: =INPUTS!$B$5
A6: Exit enterprise value | B6: =B4*B5
A7: Less: net debt at exit | B7: =DEBT!F33
A8: Exit equity value | B8: =B6-B7
A9: Sponsor equity at entry | B9: =SOURCES_USES!B14
A10: Money multiple | B10: =B8/B9
A11: Holding period (years) | B11: =COLUMNS(PROJECTION!B5:F5)
A12: IRR | B12: =IF(OR(B9<=0,B8<=0),NA(),B10^(1/B11)-1)
A14: Where the value came from
A15: EBITDA growth | B15: =(B4-SOURCES_USES!B4)*INPUTS!$B$4 | C15: Growth in earnings, valued at the entry multiple
A16: Multiple change | B16: =(INPUTS!$B$5-INPUTS!$B$4)*B4 | C16: Re-rating, applied to exit earnings. The component you do not control
A17: Debt paydown and cash generation | B17: =SOURCES_USES!B25-B7 | C17: Net debt reduction over the hold
A18: Total value created | B18: =B15+B16+B17
A19: Check: total − (exit equity − entry equity) | B19: =B18-(B8-SOURCES_USES!B26) | C19: Must be zero — the attribution is an identity

Sheet SENSITIVITY
A1: SENSITIVITY — IRR: entry multiple vs exit multiple
A2: Both axes are driven off INPUTS by the step cells (B14/B15). Buying cheaply and selling dearly is the whole grid.
B3: Entry ↓ / Exit →
C4: =INPUTS!$B$5+(COLUMN(C4)-5)*INPUTS!$B$15 | D4: =INPUTS!$B$5+(COLUMN(D4)-5)*INPUTS!$B$15 | E4: =INPUTS!$B$5+(COLUMN(E4)-5)*INPUTS!$B$15 | F4: =INPUTS!$B$5+(COLUMN(F4)-5)*INPUTS!$B$15 | G4: =INPUTS!$B$5+(COLUMN(G4)-5)*INPUTS!$B$15
B5: =INPUTS!$B$4+(ROW(B5)-7)*INPUTS!$B$14 | C5: =IF(OR(($B5*SOURCES_USES!$B$4*(1+INPUTS!$B$6)+SOURCES_USES!$B$20+INPUTS!$B$12-SOURCES_USES!$B$12-INPUTS!$B$8)<=0,(C$4*RETURNS!$B$4-RETURNS!$B$7)<=0),NA(),((C$4*RETURNS!$B$4-RETURNS!$B$7)/($B5*SOURCES_USES!$B$4*(1+INPUTS!$B$6)+SOURCES_USES!$B$20+INPUTS!$B$12-SOURCES_USES!$B$12-INPUTS!$B$8))^(1/RETURNS!$B$11)-1) | D5: =IF(OR(($B5*SOURCES_USES!$B$4*(1+INPUTS!$B$6)+SOURCES_USES!$B$20+INPUTS!$B$12-SOURCES_USES!$B$12-INPUTS!$B$8)<=0,(D$4*RETURNS!$B$4-RETURNS!$B$7)<=0),NA(),((D$4*RETURNS!$B$4-RETURNS!$B$7)/($B5*SOURCES_USES!$B$4*(1+INPUTS!$B$6)+SOURCES_USES!$B$20+INPUTS!$B$12-SOURCES_USES!$B$12-INPUTS!$B$8))^(1/RETURNS!$B$11)-1) | E5: =IF(OR(($B5*SOURCES_USES!$B$4*(1+INPUTS!$B$6)+SOURCES_USES!$B$20+INPUTS!$B$12-SOURCES_USES!$B$12-INPUTS!$B$8)<=0,(E$4*RETURNS!$B$4-RETURNS!$B$7)<=0),NA(),((E$4*RETURNS!$B$4-RETURNS!$B$7)/($B5*SOURCES_USES!$B$4*(1+INPUTS!$B$6)+SOURCES_USES!$B$20+INPUTS!$B$12-SOURCES_USES!$B$12-INPUTS!$B$8))^(1/RETURNS!$B$11)-1) | F5: =IF(OR(($B5*SOURCES_USES!$B$4*(1+INPUTS!$B$6)+SOURCES_USES!$B$20+INPUTS!$B$12-SOURCES_USES!$B$12-INPUTS!$B$8)<=0,(F$4*RETURNS!$B$4-RETURNS!$B$7)<=0),NA(),((F$4*RETURNS!$B$4-RETURNS!$B$7)/($B5*SOURCES_USES!$B$4*(1+INPUTS!$B$6)+SOURCES_USES!$B$20+INPUTS!$B$12-SOURCES_USES!$B$12-INPUTS!$B$8))^(1/RETURNS!$B$11)-1) | G5: =IF(OR(($B5*SOURCES_USES!$B$4*(1+INPUTS!$B$6)+SOURCES_USES!$B$20+INPUTS!$B$12-SOURCES_USES!$B$12-INPUTS!$B$8)<=0,(G$4*RETURNS!$B$4-RETURNS!$B$7)<=0),NA(),((G$4*RETURNS!$B$4-RETURNS!$B$7)/($B5*SOURCES_USES!$B$4*(1+INPUTS!$B$6)+SOURCES_USES!$B$20+INPUTS!$B$12-SOURCES_USES!$B$12-INPUTS!$B$8))^(1/RETURNS!$B$11)-1)
B6: =INPUTS!$B$4+(ROW(B6)-7)*INPUTS!$B$14 | C6: =IF(OR(($B6*SOURCES_USES!$B$4*(1+INPUTS!$B$6)+SOURCES_USES!$B$20+INPUTS!$B$12-SOURCES_USES!$B$12-INPUTS!$B$8)<=0,(C$4*RETURNS!$B$4-RETURNS!$B$7)<=0),NA(),((C$4*RETURNS!$B$4-RETURNS!$B$7)/($B6*SOURCES_USES!$B$4*(1+INPUTS!$B$6)+SOURCES_USES!$B$20+INPUTS!$B$12-SOURCES_USES!$B$12-INPUTS!$B$8))^(1/RETURNS!$B$11)-1) | D6: =IF(OR(($B6*SOURCES_USES!$B$4*(1+INPUTS!$B$6)+SOURCES_USES!$B$20+INPUTS!$B$12-SOURCES_USES!$B$12-INPUTS!$B$8)<=0,(D$4*RETURNS!$B$4-RETURNS!$B$7)<=0),NA(),((D$4*RETURNS!$B$4-RETURNS!$B$7)/($B6*SOURCES_USES!$B$4*(1+INPUTS!$B$6)+SOURCES_USES!$B$20+INPUTS!$B$12-SOURCES_USES!$B$12-INPUTS!$B$8))^(1/RETURNS!$B$11)-1) | E6: =IF(OR(($B6*SOURCES_USES!$B$4*(1+INPUTS!$B$6)+SOURCES_USES!$B$20+INPUTS!$B$12-SOURCES_USES!$B$12-INPUTS!$B$8)<=0,(E$4*RETURNS!$B$4-RETURNS!$B$7)<=0),NA(),((E$4*RETURNS!$B$4-RETURNS!$B$7)/($B6*SOURCES_USES!$B$4*(1+INPUTS!$B$6)+SOURCES_USES!$B$20+INPUTS!$B$12-SOURCES_USES!$B$12-INPUTS!$B$8))^(1/RETURNS!$B$11)-1) | F6: =IF(OR(($B6*SOURCES_USES!$B$4*(1+INPUTS!$B$6)+SOURCES_USES!$B$20+INPUTS!$B$12-SOURCES_USES!$B$12-INPUTS!$B$8)<=0,(F$4*RETURNS!$B$4-RETURNS!$B$7)<=0),NA(),((F$4*RETURNS!$B$4-RETURNS!$B$7)/($B6*SOURCES_USES!$B$4*(1+INPUTS!$B$6)+SOURCES_USES!$B$20+INPUTS!$B$12-SOURCES_USES!$B$12-INPUTS!$B$8))^(1/RETURNS!$B$11)-1) | G6: =IF(OR(($B6*SOURCES_USES!$B$4*(1+INPUTS!$B$6)+SOURCES_USES!$B$20+INPUTS!$B$12-SOURCES_USES!$B$12-INPUTS!$B$8)<=0,(G$4*RETURNS!$B$4-RETURNS!$B$7)<=0),NA(),((G$4*RETURNS!$B$4-RETURNS!$B$7)/($B6*SOURCES_USES!$B$4*(1+INPUTS!$B$6)+SOURCES_USES!$B$20+INPUTS!$B$12-SOURCES_USES!$B$12-INPUTS!$B$8))^(1/RETURNS!$B$11)-1)
B7: =INPUTS!$B$4+(ROW(B7)-7)*INPUTS!$B$14 | C7: =IF(OR(($B7*SOURCES_USES!$B$4*(1+INPUTS!$B$6)+SOURCES_USES!$B$20+INPUTS!$B$12-SOURCES_USES!$B$12-INPUTS!$B$8)<=0,(C$4*RETURNS!$B$4-RETURNS!$B$7)<=0),NA(),((C$4*RETURNS!$B$4-RETURNS!$B$7)/($B7*SOURCES_USES!$B$4*(1+INPUTS!$B$6)+SOURCES_USES!$B$20+INPUTS!$B$12-SOURCES_USES!$B$12-INPUTS!$B$8))^(1/RETURNS!$B$11)-1) | D7: =IF(OR(($B7*SOURCES_USES!$B$4*(1+INPUTS!$B$6)+SOURCES_USES!$B$20+INPUTS!$B$12-SOURCES_USES!$B$12-INPUTS!$B$8)<=0,(D$4*RETURNS!$B$4-RETURNS!$B$7)<=0),NA(),((D$4*RETURNS!$B$4-RETURNS!$B$7)/($B7*SOURCES_USES!$B$4*(1+INPUTS!$B$6)+SOURCES_USES!$B$20+INPUTS!$B$12-SOURCES_USES!$B$12-INPUTS!$B$8))^(1/RETURNS!$B$11)-1) | E7: =IF(OR(($B7*SOURCES_USES!$B$4*(1+INPUTS!$B$6)+SOURCES_USES!$B$20+INPUTS!$B$12-SOURCES_USES!$B$12-INPUTS!$B$8)<=0,(E$4*RETURNS!$B$4-RETURNS!$B$7)<=0),NA(),((E$4*RETURNS!$B$4-RETURNS!$B$7)/($B7*SOURCES_USES!$B$4*(1+INPUTS!$B$6)+SOURCES_USES!$B$20+INPUTS!$B$12-SOURCES_USES!$B$12-INPUTS!$B$8))^(1/RETURNS!$B$11)-1) | F7: =IF(OR(($B7*SOURCES_USES!$B$4*(1+INPUTS!$B$6)+SOURCES_USES!$B$20+INPUTS!$B$12-SOURCES_USES!$B$12-INPUTS!$B$8)<=0,(F$4*RETURNS!$B$4-RETURNS!$B$7)<=0),NA(),((F$4*RETURNS!$B$4-RETURNS!$B$7)/($B7*SOURCES_USES!$B$4*(1+INPUTS!$B$6)+SOURCES_USES!$B$20+INPUTS!$B$12-SOURCES_USES!$B$12-INPUTS!$B$8))^(1/RETURNS!$B$11)-1) | G7: =IF(OR(($B7*SOURCES_USES!$B$4*(1+INPUTS!$B$6)+SOURCES_USES!$B$20+INPUTS!$B$12-SOURCES_USES!$B$12-INPUTS!$B$8)<=0,(G$4*RETURNS!$B$4-RETURNS!$B$7)<=0),NA(),((G$4*RETURNS!$B$4-RETURNS!$B$7)/($B7*SOURCES_USES!$B$4*(1+INPUTS!$B$6)+SOURCES_USES!$B$20+INPUTS!$B$12-SOURCES_USES!$B$12-INPUTS!$B$8))^(1/RETURNS!$B$11)-1)
B8: =INPUTS!$B$4+(ROW(B8)-7)*INPUTS!$B$14 | C8: =IF(OR(($B8*SOURCES_USES!$B$4*(1+INPUTS!$B$6)+SOURCES_USES!$B$20+INPUTS!$B$12-SOURCES_USES!$B$12-INPUTS!$B$8)<=0,(C$4*RETURNS!$B$4-RETURNS!$B$7)<=0),NA(),((C$4*RETURNS!$B$4-RETURNS!$B$7)/($B8*SOURCES_USES!$B$4*(1+INPUTS!$B$6)+SOURCES_USES!$B$20+INPUTS!$B$12-SOURCES_USES!$B$12-INPUTS!$B$8))^(1/RETURNS!$B$11)-1) | D8: =IF(OR(($B8*SOURCES_USES!$B$4*(1+INPUTS!$B$6)+SOURCES_USES!$B$20+INPUTS!$B$12-SOURCES_USES!$B$12-INPUTS!$B$8)<=0,(D$4*RETURNS!$B$4-RETURNS!$B$7)<=0),NA(),((D$4*RETURNS!$B$4-RETURNS!$B$7)/($B8*SOURCES_USES!$B$4*(1+INPUTS!$B$6)+SOURCES_USES!$B$20+INPUTS!$B$12-SOURCES_USES!$B$12-INPUTS!$B$8))^(1/RETURNS!$B$11)-1) | E8: =IF(OR(($B8*SOURCES_USES!$B$4*(1+INPUTS!$B$6)+SOURCES_USES!$B$20+INPUTS!$B$12-SOURCES_USES!$B$12-INPUTS!$B$8)<=0,(E$4*RETURNS!$B$4-RETURNS!$B$7)<=0),NA(),((E$4*RETURNS!$B$4-RETURNS!$B$7)/($B8*SOURCES_USES!$B$4*(1+INPUTS!$B$6)+SOURCES_USES!$B$20+INPUTS!$B$12-SOURCES_USES!$B$12-INPUTS!$B$8))^(1/RETURNS!$B$11)-1) | F8: =IF(OR(($B8*SOURCES_USES!$B$4*(1+INPUTS!$B$6)+SOURCES_USES!$B$20+INPUTS!$B$12-SOURCES_USES!$B$12-INPUTS!$B$8)<=0,(F$4*RETURNS!$B$4-RETURNS!$B$7)<=0),NA(),((F$4*RETURNS!$B$4-RETURNS!$B$7)/($B8*SOURCES_USES!$B$4*(1+INPUTS!$B$6)+SOURCES_USES!$B$20+INPUTS!$B$12-SOURCES_USES!$B$12-INPUTS!$B$8))^(1/RETURNS!$B$11)-1) | G8: =IF(OR(($B8*SOURCES_USES!$B$4*(1+INPUTS!$B$6)+SOURCES_USES!$B$20+INPUTS!$B$12-SOURCES_USES!$B$12-INPUTS!$B$8)<=0,(G$4*RETURNS!$B$4-RETURNS!$B$7)<=0),NA(),((G$4*RETURNS!$B$4-RETURNS!$B$7)/($B8*SOURCES_USES!$B$4*(1+INPUTS!$B$6)+SOURCES_USES!$B$20+INPUTS!$B$12-SOURCES_USES!$B$12-INPUTS!$B$8))^(1/RETURNS!$B$11)-1)
B9: =INPUTS!$B$4+(ROW(B9)-7)*INPUTS!$B$14 | C9: =IF(OR(($B9*SOURCES_USES!$B$4*(1+INPUTS!$B$6)+SOURCES_USES!$B$20+INPUTS!$B$12-SOURCES_USES!$B$12-INPUTS!$B$8)<=0,(C$4*RETURNS!$B$4-RETURNS!$B$7)<=0),NA(),((C$4*RETURNS!$B$4-RETURNS!$B$7)/($B9*SOURCES_USES!$B$4*(1+INPUTS!$B$6)+SOURCES_USES!$B$20+INPUTS!$B$12-SOURCES_USES!$B$12-INPUTS!$B$8))^(1/RETURNS!$B$11)-1) | D9: =IF(OR(($B9*SOURCES_USES!$B$4*(1+INPUTS!$B$6)+SOURCES_USES!$B$20+INPUTS!$B$12-SOURCES_USES!$B$12-INPUTS!$B$8)<=0,(D$4*RETURNS!$B$4-RETURNS!$B$7)<=0),NA(),((D$4*RETURNS!$B$4-RETURNS!$B$7)/($B9*SOURCES_USES!$B$4*(1+INPUTS!$B$6)+SOURCES_USES!$B$20+INPUTS!$B$12-SOURCES_USES!$B$12-INPUTS!$B$8))^(1/RETURNS!$B$11)-1) | E9: =IF(OR(($B9*SOURCES_USES!$B$4*(1+INPUTS!$B$6)+SOURCES_USES!$B$20+INPUTS!$B$12-SOURCES_USES!$B$12-INPUTS!$B$8)<=0,(E$4*RETURNS!$B$4-RETURNS!$B$7)<=0),NA(),((E$4*RETURNS!$B$4-RETURNS!$B$7)/($B9*SOURCES_USES!$B$4*(1+INPUTS!$B$6)+SOURCES_USES!$B$20+INPUTS!$B$12-SOURCES_USES!$B$12-INPUTS!$B$8))^(1/RETURNS!$B$11)-1) | F9: =IF(OR(($B9*SOURCES_USES!$B$4*(1+INPUTS!$B$6)+SOURCES_USES!$B$20+INPUTS!$B$12-SOURCES_USES!$B$12-INPUTS!$B$8)<=0,(F$4*RETURNS!$B$4-RETURNS!$B$7)<=0),NA(),((F$4*RETURNS!$B$4-RETURNS!$B$7)/($B9*SOURCES_USES!$B$4*(1+INPUTS!$B$6)+SOURCES_USES!$B$20+INPUTS!$B$12-SOURCES_USES!$B$12-INPUTS!$B$8))^(1/RETURNS!$B$11)-1) | G9: =IF(OR(($B9*SOURCES_USES!$B$4*(1+INPUTS!$B$6)+SOURCES_USES!$B$20+INPUTS!$B$12-SOURCES_USES!$B$12-INPUTS!$B$8)<=0,(G$4*RETURNS!$B$4-RETURNS!$B$7)<=0),NA(),((G$4*RETURNS!$B$4-RETURNS!$B$7)/($B9*SOURCES_USES!$B$4*(1+INPUTS!$B$6)+SOURCES_USES!$B$20+INPUTS!$B$12-SOURCES_USES!$B$12-INPUTS!$B$8))^(1/RETURNS!$B$11)-1)
B11: Shaded centre cell = base case; it must equal the IRR on RETURNS (CHECKS verifies this).

Sheet CHECKS
A1: CHECKS — live assertions, recomputed by Excel
A2: Every row must read PASS. These recompute identities independently of the cells they test.
A3: Check | B3: Result | C3: What it proves
A4: Sources equal uses | B4: =IF(ABS(SOURCES_USES!B24)<0.01,"PASS","FAIL") | C4: The entry funds itself — the sponsor cheque is the plug
A5: Attribution ties to value created | B5: =IF(ABS(RETURNS!B19)<0.01,"PASS","FAIL") | C5: EBITDA growth + multiple change + debt paydown = change in equity value, exactly
A6: No debt balance goes negative | B6: =IF(MIN(DEBT!B26:F26)>=-0.01,"PASS","FAIL") | C6: Repayment and sweep never exceed what is outstanding
A7: Cash never falls below the minimum | B7: =IF(MIN(DEBT!B32:F32)>=INPUTS!$B$11-0.01,"PASS","FAIL") | C7: The sweep leaves the minimum balance behind
A8: Debt roll-forward holds in year 1 | B8: =IF(ABS(DEBT!B8-(DEBT!B5-DEBT!B6-DEBT!B7))<0.01,"PASS","FAIL") | C8: Closing = opening - amortisation - sweep on the senior tranche
A9: Sweep never exceeds cash available | B9: =IF(SUMPRODUCT(MAX(DEBT!B25:F25-DEBT!B31:F31))<0.01,"PASS","FAIL") | C9: The sweep cannot spend money the business did not generate
A10: Interest charged on opening balances | B10: =IF(ABS(DEBT!B9-DEBT!B5*INPUTS!$C$25)<0.01,"PASS","FAIL") | C10: No circular reference in the interest calculation
A11: Money multiple ties to the equity values | B11: =IF(ABS(RETURNS!B10-RETURNS!B8/RETURNS!B9)<0.0001,"PASS","FAIL") | C11: MoM = exit equity / sponsor equity
A12: IRR is consistent with the money multiple | B12: =IF(ABS((1+RETURNS!B12)^RETURNS!B11-RETURNS!B10)<0.0001,"PASS","FAIL") | C12: (1+IRR)^years = MoM, with no interim distributions
A13: Sensitivity centre equals the headline IRR | B13: =IF(ABS(SENSITIVITY!E7-RETURNS!B12)<0.0001,"PASS","FAIL") | C13: The grid is wired to the same deal
A14: Opening leverage at or below 7.0x | B14: =IF(SOURCES_USES!B27<=7,"PASS","REVIEW") | C14: Above this, the structure is unusual enough to need saying out loud
A15: EBITDA margin at or above the historical trough | B15: =IF(MIN(INPUTS!B19:F19)>=HISTORICALS!$B$13,"PASS","REVIEW") | C15: The case does not assume the company never has a bad year again
A17: OVERALL | B17: =IF(COUNTIF(B4:B15,"FAIL")=0,"ALL PASS","FAILURES PRESENT")
