Workbook

Sheet README
A1: Testco Industries plc (TSTC) — Three-statement operating model
A3: Built | B3: 2026-10-17
A4: Currency | B4: USD
A5: Units | B5: millions
A6: Fiscal year end | B6: 31 December
A7: Generated by | B7: Financopedia build_model.py
A9: Colour key | B9: Blue = input you can change · Black = formula · Amber italic = estimated input
A10: Structure | B10: Every figure outside INPUTS and HISTORICALS is a formula. Change an input, the model moves.
A11: CHECKS tab | B11: Live assertions recomputing the model's identities. All must read PASS.
A12: History | B12: 10 reported years of income statement, balance sheet and operating cash flow
A13: DUPONT tab | B13: Return on equity split into margin, asset efficiency and leverage, on average balances
A14: Forecast | B14: 7 years, fully linked
A15: Interest | B15: Charged on opening balances, so the workbook needs no iterative calculation. It slightly understates interest in a year of heavy drawdown.
... A20: Not advice | B20: Not financial advice and not produced by a licensed advisor. Assumptions are estimates and will be wrong to some degree; the sensitivity tab exists to show by how much.

Sheet INPUTS
A1: INPUTS — every assumption behind the three statements
A2: Blue = input. Amber italic = estimated. Interest is charged on opening balances, so the model needs no iterative calculation.
A3: Assumption | B3: Value | C3: Unit | I3: Basis / source
A4: Tax rate | B4: 0.21 | C4: % | I4: FY2025 effective rate per the 10-K tax footnote
A5: Interest rate — term debt | B5: 0.055 | C5: % | I5: Weighted average coupon, FY2025 10-K debt footnote
A6: Interest rate — revolver | B6: 0.075 | C6: % | I6: Revolver margin over base rate per the credit agreement
A7: Interest earned on cash | B7: 0.03 | C7: % | I7: Short-term deposit rate, 2026-10-16
A8: Minimum cash balance | B8: 250 | C8: millions | I8: Management's stated minimum operating cash (Q4 FY2025 call)
A9: Dividend payout ratio | B9: 0.3 | C9: % | I9: ESTIMATE: FY2023-FY2025 average payout
A10: Opening revolver balance | B10: 0 | C10: millions | I10: Nil drawn at FY2025 year end per the 10-K
A12: Forecast driver | B12: Y1 | C12: Y2 | D12: Y3 | E12: Y4 | F12: Y5 | G12: Y6 | H12: Y7 | I12: Basis / source
A13: Revenue growth | B13: 0.075 | C13: 0.068 | D13: 0.06 | E13: 0.052 | F13: 0.045 | G13: 0.04 | H13: 0.035 | I13: Y1 guided (Q4 FY2025 call, 2026-02-14); fades toward the 10-year CAGR
A14: Gross margin | B14: 0.415 | C14: 0.416 | D14: 0.417 | E14: 0.417 | F14: 0.418 | G14: 0.418 | H14: 0.418 | I14: ESTIMATE: held near FY2025, inside the 10-year range
A15: SG&A (% of revenue) | B15: 0.15 | C15: 0.149 | D15: 0.149 | E15: 0.148 | F15: 0.148 | G15: 0.148 | H15: 0.148 | I15: Continues the 10-year operating leverage trend
A16: D&A (% of revenue) | B16: 0.049 | C16: 0.049 | D16: 0.049 | E16: 0.049 | F16: 0.049 | G16: 0.049 | H16: 0.049 | I16: 10-year average of D&A over revenue
A17: Capex (% of revenue) | B17: 0.06 | C17: 0.059 | D17: 0.058 | E17: 0.057 | F17: 0.056 | G17: 0.055 | H17: 0.055 | I17: Y1 guided capex; fades to the 10-year average
A18: Days sales outstanding | B18: 52 | C18: 52 | D18: 52 | E18: 52 | F18: 52 | G18: 52 | H18: 52 | I18: 10-year average receivable days
A19: Days inventory outstanding | B19: 68 | C19: 68 | D19: 68 | E19: 68 | F19: 68 | G19: 68 | H19: 68 | I19: 10-year average inventory days
A20: Days payables outstanding | B20: 55 | C20: 55 | D20: 55 | E20: 55 | F20: 55 | G20: 55 | H20: 55 | I20: 10-year average payable days
A21: Other current assets (% of revenue) | B21: 0.03 | C21: 0.03 | D21: 0.03 | E21: 0.03 | F21: 0.03 | G21: 0.03 | H21: 0.03 | I21: ESTIMATE: 10-year average
A22: Accrued liabilities (% of revenue) | B22: 0.05 | C22: 0.05 | D22: 0.05 | E22: 0.05 | F22: 0.05 | G22: 0.05 | H22: 0.05 | I22: ESTIMATE: 10-year average
A23: Scheduled term debt repayment | B23: 80 | C23: 80 | D23: 80 | E23: 80 | F23: 80 | G23: 80 | H23: 80 | I23: Contractual amortisation per the FY2025 10-K debt footnote

Sheet HISTORICALS
A1: HISTORICALS — 10 reported years of income statement and balance sheet
A2: Blue = as reported. The balance row proves each year's reported balance sheet actually balances.
A3: Line item | B3: 2016 | C3: 2017 | D3: 2018 | E3: 2019 | F3: 2020 | G3: 2021 | H3: 2022 | I3: 2023 | J3: 2024 | K3: 2025 | L3: Source (filing, date)
A4: Revenue | B4: 2150 | C4: 2365 | D4: 2580 | E4: 2790 | F4: 2510 | G4: 2980 | H4: 3320 | I4: 3610 | J4: 3940 | K4: 4280 | L4: FY2016-FY2025 10-K filings; FY2025 filed 2026-02-14 (revenue)
A5: Cost of goods sold | B5: 1322.2 | C5: 1445 | D5: 1568.6 | E5: 1688 | F5: 1601.4 | G5: 1788 | H5: 1975.4 | I5: 2137.1 | J5: 2320.7 | K5: 2508.1 | L5: FY2016-FY2025 10-K filings; FY2025 filed 2026-02-14 (cogs)
A6: Gross profit | B6: =B4-B5 | C6: =C4-C5 | D6: =D4-D5 | E6: =E4-E5 | F6: =F4-F5 | G6: =G4-G5 | H6: =H4-H5 | I6: =I4-I5 | ... K6: =K4-K5
A7: SG&A | B7: 354.8 | C7: 385.5 | D7: 418 | E7: 449.2 | F7: 431.7 | G7: 467.9 | H7: 514.6 | I7: 552.3 | J7: 598.9 | K7: 642 | L7: FY2016-FY2025 10-K filings; FY2025 filed 2026-02-14 (sga)
A8: EBITDA | B8: =B6-B7 | C8: =C6-C7 | D8: =D6-D7 | E8: =E6-E7 | F8: =F6-F7 | G8: =G6-G7 | H8: =H6-H7 | I8: =I6-I7 | ... K8: =K6-K7
A9: D&A | B9: 105.4 | C9: 115.9 | D9: 126.4 | E9: 136.7 | F9: 123 | G9: 146 | H9: 162.7 | I9: 176.9 | J9: 193.1 | K9: 209.7 | L9: FY2016-FY2025 10-K filings; FY2025 filed 2026-02-14 (da)
A10: EBIT | B10: =B8-B9 | C10: =C8-C9 | D10: =D8-D9 | E10: =E8-E9 | F10: =F8-F9 | G10: =G8-G9 | H10: =H8-H9 | I10: =I8-I9 | ... K10: =K8-K9
A11: Capex | B11: 133.3 | C11: 153.7 | D11: 157.4 | E11: 161.8 | F11: 102.9 | G11: 175.8 | H11: 209.2 | I11: 216.6 | J11: 228.5 | K11: 256.8 | L11: FY2016-FY2025 10-K filings; FY2025 filed 2026-02-14 (capex)
A13: Cash and equivalents | B13: 176.3 | C13: 193.9 | D13: 211.6 | E13: 228.8 | F13: 205.8 | G13: 244.4 | H13: 272.2 | I13: 296 | J13: 323.1 | K13: 351 | L13: FY2016-FY2025 10-K filings; FY2025 filed 2026-02-14 (cash)
A14: Accounts receivable | B14: 306.3 | C14: 336.9 | D14: 367.6 | E14: 397.5 | F14: 357.6 | G14: 424.5 | H14: 473 | I14: 514.3 | J14: 561.3 | K14: 609.8 | L14: FY2016-FY2025 10-K filings; FY2025 filed 2026-02-14 (ar)
A15: Inventory | B15: 246.3 | C15: 269.2 | D15: 292.2 | E15: 314.5 | F15: 298.3 | G15: 333.1 | H15: 368 | I15: 398.1 | J15: 432.3 | K15: 467.3 | L15: FY2016-FY2025 10-K filings; FY2025 filed 2026-02-14 (inventory)
A16: Other current assets | B16: 64.5 | C16: 71 | D16: 77.4 | E16: 83.7 | F16: 75.3 | G16: 89.4 | H16: 99.6 | I16: 108.3 | J16: 118.2 | K16: 128.4 | L16: FY2016-FY2025 10-K filings; FY2025 filed 2026-02-14 (other_ca)
A17: Net PP&E | B17: 1182.5 | C17: 1300.8 | D17: 1419 | E17: 1534.5 | F17: 1380.5 | G17: 1639 | H17: 1826 | I17: 1985.5 | J17: 2167 | K17: 2354 | L17: FY2016-FY2025 10-K filings; FY2025 filed 2026-02-14 (ppe_net)
A18: Other assets | B18: 200 | C18: 200 | D18: 200 | E18: 200 | F18: 200 | G18: 200 | H18: 200 | I18: 200 | J18: 200 | K18: 200 | L18: FY2016-FY2025 10-K filings; FY2025 filed 2026-02-14 (other_assets)
A19: Total assets | B19: =SUM(B13:B18) | C19: =SUM(C13:C18) | D19: =SUM(D13:D18) | E19: =SUM(E13:E18) | F19: =SUM(F13:F18) | G19: =SUM(G13:G18) | H19: =SUM(H13:H18) | I19: =SUM(I13:I18) | ... K19: =SUM(K13:K18)
A21: Accounts payable | B21: 199.2 | C21: 217.7 | D21: 236.4 | E21: 254.4 | F21: 241.3 | G21: 269.4 | H21: 297.7 | I21: 322 | J21: 349.7 | K21: 377.9 | L21: FY2016-FY2025 10-K filings; FY2025 filed 2026-02-14 (ap)
A22: Accrued liabilities | B22: 107.5 | C22: 118.2 | D22: 129 | E22: 139.5 | F22: 125.5 | G22: 149 | H22: 166 | I22: 180.5 | J22: 197 | K22: 214 | L22: FY2016-FY2025 10-K filings; FY2025 filed 2026-02-14 (accrued)
A23: Other current liabilities | B23: 120 | C23: 120 | D23: 120 | E23: 120 | F23: 120 | G23: 120 | H23: 120 | I23: 120 | J23: 120 | K23: 120 | L23: FY2016-FY2025 10-K filings; FY2025 filed 2026-02-14 (other_cl)
A24: Total debt | B24: 1850 | C24: 1800 | D24: 1750 | E24: 1700 | F24: 1780 | G24: 1700 | H24: 1620 | I24: 1540 | J24: 1460 | K24: 1380 | L24: FY2016-FY2025 10-K filings; FY2025 filed 2026-02-14 (debt)
A25: Other long-term liabilities | B25: 180 | C25: 180 | D25: 180 | E25: 180 | F25: 180 | G25: 180 | H25: 180 | I25: 180 | J25: 180 | K25: 180 | L25: FY2016-FY2025 10-K filings; FY2025 filed 2026-02-14 (other_lt_liab)
A26: Shareholders' equity | B26: -280.8 | C26: -64.1 | D26: 152.4 | E26: 365.1 | F26: 70.7 | G26: 512 | H26: 855.1 | I26: 1159.7 | J26: 1495.2 | K26: 1838.6 | L26: FY2016-FY2025 10-K filings; FY2025 filed 2026-02-14 (equity)
A27: Total liabilities and equity | B27: =SUM(B21:B26) | C27: =SUM(C21:C26) | D27: =SUM(D21:D26) | E27: =SUM(E21:E26) | F27: =SUM(F21:F26) | G27: =SUM(G21:G26) | H27: =SUM(H21:H26) | I27: =SUM(I21:I26) | ... K27: =SUM(K21:K26)
A28: Balance check (assets − L&E) | B28: =B19-B27 | C28: =C19-C27 | D28: =D19-D27 | E28: =E19-E27 | F28: =F19-F27 | G28: =G19-G27 | H28: =H19-H27 | I28: =I19-I27 | ... K28: =K19-K27
A29: Net working capital (memo) | B29: =B14+B15+B16-B21-B22 | C29: =C14+C15+C16-C21-C22 | D29: =D14+D15+D16-D21-D22 | E29: =E14+E15+E16-E21-E22 | F29: =F14+F15+F16-F21-F22 | G29: =G14+G15+G16-G21-G22 | H29: =H14+H15+H16-H21-H22 | I29: =I14+I15+I16-I21-I22 | ... K29: =K14+K15+K16-K21-K22
A35: Income statement and cash flow, reported
A36: Net income | B36: 210 | C36: 252.5 | D36: 292.9 | E36: 333.9 | F36: 202.2 | G36: 382.8 | H36: 456.8 | I36: 520.6 | J36: 590.1 | K36: 667 | L36: FY2016-FY2025 10-K filings; FY2025 filed 2026-02-14 (net_income)
A37: Interest expense | B37: 101.8 | C37: 99 | D37: 96.2 | E37: 93.5 | F37: 97.9 | G37: 93.5 | H37: 89.1 | I37: 84.7 | J37: 80.3 | K37: 75.9 | L37: FY2016-FY2025 10-K filings; FY2025 filed 2026-02-14 (interest_expense)
A38: Cash from operating activities | B38: 272.4 | C38: 321.1 | D38: 367.7 | E38: 414.8 | F38: 275 | G38: 469.2 | H38: 553.1 | I38: 625.3 | J38: 704.4 | K38: 791.1 | L38: FY2016-FY2025 10-K filings; FY2025 filed 2026-02-14 (cfo)
A40: What 10 years of history says
A41: Revenue CAGR over the period | B41: =((K4/B4)^(1/9))-1 | C41: Compare with the projected growth on INPUTS
A42: Gross margin — average | B42: =AVERAGE(B6:K6)/AVERAGE(B4:K4)
A43: EBITDA margin — average | B43: =AVERAGE(B8:K8)/AVERAGE(B4:K4)
A44: EBITDA margin — worst year | B44: =MIN(B8:K8/B4:K4) | C44: The trough the forecast should be tested against

Sheet INCOME
A1: INCOME STATEMENT — forecast
A2: Interest is charged on opening balances, which is why no cell here refers to this year's closing debt.
A3: Line item | B3: 2026 | C3: 2027 | D3: 2028 | E3: 2029 | F3: 2030 | G3: 2031 | H3: 2032
A4: Revenue | B4: =HISTORICALS!$K$4*(1+INPUTS!B$13) | C4: =B4*(1+INPUTS!C$13) | D4: =C4*(1+INPUTS!D$13) | E4: =D4*(1+INPUTS!E$13) | F4: =E4*(1+INPUTS!F$13) | G4: =F4*(1+INPUTS!G$13) | H4: =G4*(1+INPUTS!H$13)
A5: Cost of goods sold | B5: =B4*(1-INPUTS!B$14) | C5: =C4*(1-INPUTS!C$14) | D5: =D4*(1-INPUTS!D$14) | E5: =E4*(1-INPUTS!E$14) | F5: =F4*(1-INPUTS!F$14) | G5: =G4*(1-INPUTS!G$14) | H5: =H4*(1-INPUTS!H$14)
A6: Gross profit | B6: =B4-B5 | C6: =C4-C5 | D6: =D4-D5 | E6: =E4-E5 | F6: =F4-F5 | G6: =G4-G5 | H6: =H4-H5
A7: SG&A | B7: =B4*INPUTS!B$15 | C7: =C4*INPUTS!C$15 | D7: =D4*INPUTS!D$15 | E7: =E4*INPUTS!E$15 | F7: =F4*INPUTS!F$15 | G7: =G4*INPUTS!G$15 | H7: =H4*INPUTS!H$15
A8: EBITDA | B8: =B6-B7 | C8: =C6-C7 | D8: =D6-D7 | E8: =E6-E7 | F8: =F6-F7 | G8: =G6-G7 | H8: =H6-H7
A9: D&A | B9: =B4*INPUTS!B$16 | C9: =C4*INPUTS!C$16 | D9: =D4*INPUTS!D$16 | E9: =E4*INPUTS!E$16 | F9: =F4*INPUTS!F$16 | G9: =G4*INPUTS!G$16 | H9: =H4*INPUTS!H$16
A10: EBIT | B10: =B8-B9 | C10: =C8-C9 | D10: =D8-D9 | E10: =E8-E9 | F10: =F8-F9 | G10: =G8-G9 | H10: =H8-H9
A11: Interest expense | B11: =HISTORICALS!$K$24*INPUTS!$B$5+INPUTS!$B$10*INPUTS!$B$6 | C11: =BALANCE!B15*INPUTS!$B$5+BALANCE!B16*INPUTS!$B$6 | D11: =BALANCE!C15*INPUTS!$B$5+BALANCE!C16*INPUTS!$B$6 | E11: =BALANCE!D15*INPUTS!$B$5+BALANCE!D16*INPUTS!$B$6 | F11: =BALANCE!E15*INPUTS!$B$5+BALANCE!E16*INPUTS!$B$6 | G11: =BALANCE!F15*INPUTS!$B$5+BALANCE!F16*INPUTS!$B$6 | H11: =BALANCE!G15*INPUTS!$B$5+BALANCE!G16*INPUTS!$B$6
A12: Interest income | B12: =HISTORICALS!$K$13*INPUTS!$B$7 | C12: =BALANCE!B4*INPUTS!$B$7 | D12: =BALANCE!C4*INPUTS!$B$7 | E12: =BALANCE!D4*INPUTS!$B$7 | F12: =BALANCE!E4*INPUTS!$B$7 | G12: =BALANCE!F4*INPUTS!$B$7 | H12: =BALANCE!G4*INPUTS!$B$7
A13: Profit before tax | B13: =B10-B11+B12 | C13: =C10-C11+C12 | D13: =D10-D11+D12 | E13: =E10-E11+E12 | F13: =F10-F11+F12 | G13: =G10-G11+G12 | H13: =H10-H11+H12
A14: Tax | B14: =MAX(B13,0)*INPUTS!$B$4 | C14: =MAX(C13,0)*INPUTS!$B$4 | D14: =MAX(D13,0)*INPUTS!$B$4 | E14: =MAX(E13,0)*INPUTS!$B$4 | F14: =MAX(F13,0)*INPUTS!$B$4 | G14: =MAX(G13,0)*INPUTS!$B$4 | H14: =MAX(H13,0)*INPUTS!$B$4
A15: Net income | B15: =B13-B14 | C15: =C13-C14 | D15: =D13-D14 | E15: =E13-E14 | F15: =F13-F14 | G15: =G13-G14 | H15: =H13-H14
A16: Dividends declared | B16: =MAX(B15,0)*INPUTS!$B$9 | C16: =MAX(C15,0)*INPUTS!$B$9 | D16: =MAX(D15,0)*INPUTS!$B$9 | E16: =MAX(E15,0)*INPUTS!$B$9 | F16: =MAX(F15,0)*INPUTS!$B$9 | G16: =MAX(G15,0)*INPUTS!$B$9 | H16: =MAX(H15,0)*INPUTS!$B$9
A17: Retained earnings | B17: =B15-B16 | C17: =C15-C16 | D17: =D15-D16 | E17: =E15-E16 | F17: =F15-F16 | G17: =G15-G16 | H17: =H15-H16

Sheet BALANCE
A1: BALANCE SHEET — forecast
A2: Other assets and other liabilities are held flat from the last reported balance sheet; they are not forecast.
A3: Line item | B3: 2026 | C3: 2027 | D3: 2028 | E3: 2029 | F3: 2030 | G3: 2031 | H3: 2032
A4: Cash and equivalents | B4: =CASHFLOW!B18 | C4: =CASHFLOW!C18 | D4: =CASHFLOW!D18 | E4: =CASHFLOW!E18 | F4: =CASHFLOW!F18 | G4: =CASHFLOW!G18 | H4: =CASHFLOW!H18
A5: Accounts receivable | B5: =INCOME!B4/365*INPUTS!B$18 | C5: =INCOME!C4/365*INPUTS!C$18 | D5: =INCOME!D4/365*INPUTS!D$18 | E5: =INCOME!E4/365*INPUTS!E$18 | F5: =INCOME!F4/365*INPUTS!F$18 | G5: =INCOME!G4/365*INPUTS!G$18 | H5: =INCOME!H4/365*INPUTS!H$18
A6: Inventory | B6: =INCOME!B5/365*INPUTS!B$19 | C6: =INCOME!C5/365*INPUTS!C$19 | D6: =INCOME!D5/365*INPUTS!D$19 | E6: =INCOME!E5/365*INPUTS!E$19 | F6: =INCOME!F5/365*INPUTS!F$19 | G6: =INCOME!G5/365*INPUTS!G$19 | H6: =INCOME!H5/365*INPUTS!H$19
A7: Other current assets | B7: =INCOME!B4*INPUTS!B$21 | C7: =INCOME!C4*INPUTS!C$21 | D7: =INCOME!D4*INPUTS!D$21 | E7: =INCOME!E4*INPUTS!E$21 | F7: =INCOME!F4*INPUTS!F$21 | G7: =INCOME!G4*INPUTS!G$21 | H7: =INCOME!H4*INPUTS!H$21
A8: Net PP&E | B8: =HISTORICALS!$K$17-CASHFLOW!B8-INCOME!B9 | C8: =B8-CASHFLOW!C8-INCOME!C9 | D8: =C8-CASHFLOW!D8-INCOME!D9 | E8: =D8-CASHFLOW!E8-INCOME!E9 | F8: =E8-CASHFLOW!F8-INCOME!F9 | G8: =F8-CASHFLOW!G8-INCOME!G9 | H8: =G8-CASHFLOW!H8-INCOME!H9
A9: Other assets (held flat) | B9: =HISTORICALS!$K$18 | C9: =HISTORICALS!$K$18 | D9: =HISTORICALS!$K$18 | E9: =HISTORICALS!$K$18 | F9: =HISTORICALS!$K$18 | G9: =HISTORICALS!$K$18 | H9: =HISTORICALS!$K$18
A10: Total assets | B10: =SUM(B4:B9) | C10: =SUM(C4:C9) | D10: =SUM(D4:D9) | E10: =SUM(E4:E9) | F10: =SUM(F4:F9) | G10: =SUM(G4:G9) | H10: =SUM(H4:H9)
A12: Accounts payable | B12: =INCOME!B5/365*INPUTS!B$20 | C12: =INCOME!C5/365*INPUTS!C$20 | D12: =INCOME!D5/365*INPUTS!D$20 | E12: =INCOME!E5/365*INPUTS!E$20 | F12: =INCOME!F5/365*INPUTS!F$20 | G12: =INCOME!G5/365*INPUTS!G$20 | H12: =INCOME!H5/365*INPUTS!H$20
A13: Accrued liabilities | B13: =INCOME!B4*INPUTS!B$22 | C13: =INCOME!C4*INPUTS!C$22 | D13: =INCOME!D4*INPUTS!D$22 | E13: =INCOME!E4*INPUTS!E$22 | F13: =INCOME!F4*INPUTS!F$22 | G13: =INCOME!G4*INPUTS!G$22 | H13: =INCOME!H4*INPUTS!H$22
A14: Other current liabilities (held flat) | B14: =HISTORICALS!$K$23 | C14: =HISTORICALS!$K$23 | D14: =HISTORICALS!$K$23 | E14: =HISTORICALS!$K$23 | F14: =HISTORICALS!$K$23 | G14: =HISTORICALS!$K$23 | H14: =HISTORICALS!$K$23
A15: Term debt | B15: =HISTORICALS!$K$24+CASHFLOW!B10 | C15: =B15+CASHFLOW!C10 | D15: =C15+CASHFLOW!D10 | E15: =D15+CASHFLOW!E10 | F15: =E15+CASHFLOW!F10 | G15: =F15+CASHFLOW!G10 | H15: =G15+CASHFLOW!H10
A16: Revolver | B16: =INPUTS!$B$10+CASHFLOW!B14+CASHFLOW!B15 | C16: =B16+CASHFLOW!C14+CASHFLOW!C15 | D16: =C16+CASHFLOW!D14+CASHFLOW!D15 | E16: =D16+CASHFLOW!E14+CASHFLOW!E15 | F16: =E16+CASHFLOW!F14+CASHFLOW!F15 | G16: =F16+CASHFLOW!G14+CASHFLOW!G15 | H16: =G16+CASHFLOW!H14+CASHFLOW!H15
A17: Other long-term liabilities (held flat) | B17: =HISTORICALS!$K$25 | C17: =HISTORICALS!$K$25 | D17: =HISTORICALS!$K$25 | E17: =HISTORICALS!$K$25 | F17: =HISTORICALS!$K$25 | G17: =HISTORICALS!$K$25 | H17: =HISTORICALS!$K$25
A18: Shareholders' equity | B18: =HISTORICALS!$K$26+INCOME!B17 | C18: =B18+INCOME!C17 | D18: =C18+INCOME!D17 | E18: =D18+INCOME!E17 | F18: =E18+INCOME!F17 | G18: =F18+INCOME!G17 | H18: =G18+INCOME!H17
A19: Total liabilities and equity | B19: =SUM(B12:B18) | C19: =SUM(C12:C18) | D19: =SUM(D12:D18) | E19: =SUM(E12:E18) | F19: =SUM(F12:F18) | G19: =SUM(G12:G18) | H19: =SUM(H12:H18)
A21: Balance check (assets − L&E) | B21: =B10-B19 | C21: =C10-C19 | D21: =D10-D19 | E21: =E10-E19 | F21: =F10-F19 | G21: =G10-G19 | H21: =H10-H19
A23: Net working capital (memo) | B23: =B5+B6+B7-B12-B13 | C23: =C5+C6+C7-C12-C13 | D23: =D5+D6+D7-D12-D13 | E23: =E5+E6+E7-E12-E13 | F23: =F5+F6+F7-F12-F13 | G23: =G5+G6+G7-G12-G13 | H23: =H5+H6+H7-H12-H13
A24: Net debt (memo) | B24: =B15+B16-B4 | C24: =C15+C16-C4 | D24: =D15+D16-D4 | E24: =E15+E16-E4 | F24: =F15+F16-F4 | G24: =G15+G16-G4 | H24: =H15+H16-H4

Sheet CASHFLOW
A1: CASH FLOW STATEMENT — forecast
A2: The revolver is the plug: it draws to hold the minimum cash balance and sweeps surplus cash to repay itself.
A3: Line item | B3: 2026 | C3: 2027 | D3: 2028 | E3: 2029 | F3: 2030 | G3: 2031 | H3: 2032
A4: Net income | B4: =INCOME!B15 | C4: =INCOME!C15 | D4: =INCOME!D15 | E4: =INCOME!E15 | F4: =INCOME!F15 | G4: =INCOME!G15 | H4: =INCOME!H15
A5: Add back: D&A | B5: =INCOME!B9 | C5: =INCOME!C9 | D5: =INCOME!D9 | E5: =INCOME!E9 | F5: =INCOME!F9 | G5: =INCOME!G9 | H5: =INCOME!H9
A6: Change in working capital | B6: =-(BALANCE!B23-HISTORICALS!$K$29) | C6: =-(BALANCE!C23-BALANCE!B23) | D6: =-(BALANCE!D23-BALANCE!C23) | E6: =-(BALANCE!E23-BALANCE!D23) | F6: =-(BALANCE!F23-BALANCE!E23) | G6: =-(BALANCE!G23-BALANCE!F23) | H6: =-(BALANCE!H23-BALANCE!G23)
A7: Cash from operations | B7: =B4+B5+B6 | C7: =C4+C5+C6 | D7: =D4+D5+D6 | E7: =E4+E5+E6 | F7: =F4+F5+F6 | G7: =G4+G5+G6 | H7: =H4+H5+H6
A8: Capex | B8: =-INCOME!B4*INPUTS!B$17 | C8: =-INCOME!C4*INPUTS!C$17 | D8: =-INCOME!D4*INPUTS!D$17 | E8: =-INCOME!E4*INPUTS!E$17 | F8: =-INCOME!F4*INPUTS!F$17 | G8: =-INCOME!G4*INPUTS!G$17 | H8: =-INCOME!H4*INPUTS!H$17
A9: Cash from investing | B9: =B8 | C9: =C8 | D9: =D8 | E9: =E8 | F9: =F8 | G9: =G8 | H9: =H8
A10: Term debt repayment | B10: =-MIN(INPUTS!B$23,HISTORICALS!$K$24) | C10: =-MIN(INPUTS!C$23,BALANCE!B15) | D10: =-MIN(INPUTS!D$23,BALANCE!C15) | E10: =-MIN(INPUTS!E$23,BALANCE!D15) | F10: =-MIN(INPUTS!F$23,BALANCE!E15) | G10: =-MIN(INPUTS!G$23,BALANCE!F15) | H10: =-MIN(INPUTS!H$23,BALANCE!G15)
A11: Dividends paid | B11: =-INCOME!B16 | C11: =-INCOME!C16 | D11: =-INCOME!D16 | E11: =-INCOME!E16 | F11: =-INCOME!F16 | G11: =-INCOME!G16 | H11: =-INCOME!H16
A12: Opening cash | B12: =HISTORICALS!$K$13 | C12: =BALANCE!B4 | D12: =BALANCE!C4 | E12: =BALANCE!D4 | F12: =BALANCE!E4 | G12: =BALANCE!F4 | H12: =BALANCE!G4
A13: Cash before revolver | B13: =B12+B7+B9+B10+B11 | C13: =C12+C7+C9+C10+C11 | D13: =D12+D7+D9+D10+D11 | E13: =E12+E7+E9+E10+E11 | F13: =F12+F7+F9+F10+F11 | G13: =G12+G7+G9+G10+G11 | H13: =H12+H7+H9+H10+H11
A14: Revolver draw | B14: =MAX(0,INPUTS!$B$8-B13) | C14: =MAX(0,INPUTS!$B$8-C13) | D14: =MAX(0,INPUTS!$B$8-D13) | E14: =MAX(0,INPUTS!$B$8-E13) | F14: =MAX(0,INPUTS!$B$8-F13) | G14: =MAX(0,INPUTS!$B$8-G13) | H14: =MAX(0,INPUTS!$B$8-H13)
A15: Revolver repayment | B15: =-MIN(INPUTS!$B$10,MAX(0,B13-INPUTS!$B$8)) | C15: =-MIN(BALANCE!B16,MAX(0,C13-INPUTS!$B$8)) | D15: =-MIN(BALANCE!C16,MAX(0,D13-INPUTS!$B$8)) | E15: =-MIN(BALANCE!D16,MAX(0,E13-INPUTS!$B$8)) | F15: =-MIN(BALANCE!E16,MAX(0,F13-INPUTS!$B$8)) | G15: =-MIN(BALANCE!F16,MAX(0,G13-INPUTS!$B$8)) | H15: =-MIN(BALANCE!G16,MAX(0,H13-INPUTS!$B$8))
A16: Cash from financing | B16: =B10+B11+B14+B15 | C16: =C10+C11+C14+C15 | D16: =D10+D11+D14+D15 | E16: =E10+E11+E14+E15 | F16: =F10+F11+F14+F15 | G16: =G10+G11+G14+G15 | H16: =H10+H11+H14+H15
A17: Net change in cash | B17: =B7+B9+B16 | C17: =C7+C9+C16 | D17: =D7+D9+D16 | E17: =E7+E9+E16 | F17: =F7+F9+F16 | G17: =G7+G9+G16 | H17: =H7+H9+H16
A18: Closing cash | B18: =B12+B17 | C18: =C12+C17 | D18: =D12+D17 | E18: =E12+E17 | F18: =F12+F17 | G18: =G12+G17 | H18: =H12+H17
A20: Unlevered free cash flow (memo) | B20: =INCOME!B10*(1-INPUTS!$B$4)+INCOME!B9+B8+B6 | C20: =INCOME!C10*(1-INPUTS!$B$4)+INCOME!C9+C8+C6 | D20: =INCOME!D10*(1-INPUTS!$B$4)+INCOME!D9+D8+D6 | E20: =INCOME!E10*(1-INPUTS!$B$4)+INCOME!E9+E8+E6 | F20: =INCOME!F10*(1-INPUTS!$B$4)+INCOME!F9+F8+F6 | G20: =INCOME!G10*(1-INPUTS!$B$4)+INCOME!G9+G8+G6 | H20: =INCOME!H10*(1-INPUTS!$B$4)+INCOME!H9+H8+H6
A21: Levered free cash flow (memo) | B21: =B7+B9 | C21: =C7+C9 | D21: =D7+D9 | E21: =E7+E9 | F21: =F7+F9 | G21: =G7+G9 | H21: =H7+H9

Sheet RATIOS
A1: RATIOS — history and forecast on one line, so the break shows
A2: If a ratio steps sharply at the forecast boundary, the assumption behind it needs a reason.
A3: Ratio | B3: 2016 | C3: 2017 | D3: 2018 | E3: 2019 | F3: 2020 | G3: 2021 | H3: 2022 | I3: 2023 | J3: 2024 | K3: 2025 | L3: 2026 | M3: 2027 | N3: 2028 | O3: 2029 | P3: 2030 | Q3: 2031 | R3: 2032
A4: Revenue growth | B4: =NA() | C4: =HISTORICALS!C4/HISTORICALS!B4-1 | D4: =HISTORICALS!D4/HISTORICALS!C4-1 | E4: =HISTORICALS!E4/HISTORICALS!D4-1 | F4: =HISTORICALS!F4/HISTORICALS!E4-1 | G4: =HISTORICALS!G4/HISTORICALS!F4-1 | H4: =HISTORICALS!H4/HISTORICALS!G4-1 | I4: =HISTORICALS!I4/HISTORICALS!H4-1 | J4: =HISTORICALS!J4/HISTORICALS!I4-1 | K4: =HISTORICALS!K4/HISTORICALS!J4-1 | L4: =INCOME!B4/HISTORICALS!$K$4-1 | M4: =INCOME!C4/INCOME!B4-1 | N4: =INCOME!D4/INCOME!C4-1 | O4: =INCOME!E4/INCOME!D4-1 | P4: =INCOME!F4/INCOME!E4-1 | Q4: =INCOME!G4/INCOME!F4-1 | R4: =INCOME!H4/INCOME!G4-1
A5: EBITDA growth | B5: =NA() | C5: =HISTORICALS!C8/HISTORICALS!B8-1 | D5: =HISTORICALS!D8/HISTORICALS!C8-1 | E5: =HISTORICALS!E8/HISTORICALS!D8-1 | F5: =HISTORICALS!F8/HISTORICALS!E8-1 | G5: =HISTORICALS!G8/HISTORICALS!F8-1 | H5: =HISTORICALS!H8/HISTORICALS!G8-1 | I5: =HISTORICALS!I8/HISTORICALS!H8-1 | J5: =HISTORICALS!J8/HISTORICALS!I8-1 | K5: =HISTORICALS!K8/HISTORICALS!J8-1 | L5: =INCOME!B8/HISTORICALS!$K$8-1 | M5: =INCOME!C8/INCOME!B8-1 | N5: =INCOME!D8/INCOME!C8-1 | O5: =INCOME!E8/INCOME!D8-1 | P5: =INCOME!F8/INCOME!E8-1 | Q5: =INCOME!G8/INCOME!F8-1 | R5: =INCOME!H8/INCOME!G8-1
A6: Gross margin | B6: =HISTORICALS!B6/HISTORICALS!B4 | C6: =HISTORICALS!C6/HISTORICALS!C4 | D6: =HISTORICALS!D6/HISTORICALS!D4 | E6: =HISTORICALS!E6/HISTORICALS!E4 | F6: =HISTORICALS!F6/HISTORICALS!F4 | G6: =HISTORICALS!G6/HISTORICALS!G4 | H6: =HISTORICALS!H6/HISTORICALS!H4 | I6: =HISTORICALS!I6/HISTORICALS!I4 | ... K6: =HISTORICALS!K6/HISTORICALS!K4 | L6: =INCOME!B6/INCOME!B4 | M6: =INCOME!C6/INCOME!C4 | N6: =INCOME!D6/INCOME!D4 | O6: =INCOME!E6/INCOME!E4 | P6: =INCOME!F6/INCOME!F4 | Q6: =INCOME!G6/INCOME!G4 | R6: =INCOME!H6/INCOME!H4
A7: EBITDA margin | B7: =HISTORICALS!B8/HISTORICALS!B4 | C7: =HISTORICALS!C8/HISTORICALS!C4 | D7: =HISTORICALS!D8/HISTORICALS!D4 | E7: =HISTORICALS!E8/HISTORICALS!E4 | F7: =HISTORICALS!F8/HISTORICALS!F4 | G7: =HISTORICALS!G8/HISTORICALS!G4 | H7: =HISTORICALS!H8/HISTORICALS!H4 | I7: =HISTORICALS!I8/HISTORICALS!I4 | ... K7: =HISTORICALS!K8/HISTORICALS!K4 | L7: =INCOME!B8/INCOME!B4 | M7: =INCOME!C8/INCOME!C4 | N7: =INCOME!D8/INCOME!D4 | O7: =INCOME!E8/INCOME!E4 | P7: =INCOME!F8/INCOME!F4 | Q7: =INCOME!G8/INCOME!G4 | R7: =INCOME!H8/INCOME!H4
A8: EBIT margin | B8: =HISTORICALS!B10/HISTORICALS!B4 | C8: =HISTORICALS!C10/HISTORICALS!C4 | D8: =HISTORICALS!D10/HISTORICALS!D4 | E8: =HISTORICALS!E10/HISTORICALS!E4 | F8: =HISTORICALS!F10/HISTORICALS!F4 | G8: =HISTORICALS!G10/HISTORICALS!G4 | H8: =HISTORICALS!H10/HISTORICALS!H4 | I8: =HISTORICALS!I10/HISTORICALS!I4 | ... K8: =HISTORICALS!K10/HISTORICALS!K4 | L8: =INCOME!B10/INCOME!B4 | M8: =INCOME!C10/INCOME!C4 | N8: =INCOME!D10/INCOME!D4 | O8: =INCOME!E10/INCOME!E4 | P8: =INCOME!F10/INCOME!F4 | Q8: =INCOME!G10/INCOME!G4 | R8: =INCOME!H10/INCOME!H4
A9: Net margin | B9: =HISTORICALS!B36/HISTORICALS!B4 | C9: =HISTORICALS!C36/HISTORICALS!C4 | D9: =HISTORICALS!D36/HISTORICALS!D4 | E9: =HISTORICALS!E36/HISTORICALS!E4 | F9: =HISTORICALS!F36/HISTORICALS!F4 | G9: =HISTORICALS!G36/HISTORICALS!G4 | H9: =HISTORICALS!H36/HISTORICALS!H4 | I9: =HISTORICALS!I36/HISTORICALS!I4 | ... K9: =HISTORICALS!K36/HISTORICALS!K4 | L9: =INCOME!B15/INCOME!B4 | M9: =INCOME!C15/INCOME!C4 | N9: =INCOME!D15/INCOME!D4 | O9: =INCOME!E15/INCOME!E4 | P9: =INCOME!F15/INCOME!F4 | Q9: =INCOME!G15/INCOME!G4 | R9: =INCOME!H15/INCOME!H4
A10: Capex % of revenue | B10: =HISTORICALS!B11/HISTORICALS!B4 | C10: =HISTORICALS!C11/HISTORICALS!C4 | D10: =HISTORICALS!D11/HISTORICALS!D4 | E10: =HISTORICALS!E11/HISTORICALS!E4 | F10: =HISTORICALS!F11/HISTORICALS!F4 | G10: =HISTORICALS!G11/HISTORICALS!G4 | H10: =HISTORICALS!H11/HISTORICALS!H4 | I10: =HISTORICALS!I11/HISTORICALS!I4 | ... K10: =HISTORICALS!K11/HISTORICALS!K4 | L10: =-CASHFLOW!B8/INCOME!B4 | M10: =-CASHFLOW!C8/INCOME!C4 | N10: =-CASHFLOW!D8/INCOME!D4 | O10: =-CASHFLOW!E8/INCOME!E4 | P10: =-CASHFLOW!F8/INCOME!F4 | Q10: =-CASHFLOW!G8/INCOME!G4 | R10: =-CASHFLOW!H8/INCOME!H4
A11: Days sales outstanding | B11: =HISTORICALS!B14/HISTORICALS!B4*365 | C11: =HISTORICALS!C14/HISTORICALS!C4*365 | D11: =HISTORICALS!D14/HISTORICALS!D4*365 | E11: =HISTORICALS!E14/HISTORICALS!E4*365 | F11: =HISTORICALS!F14/HISTORICALS!F4*365 | G11: =HISTORICALS!G14/HISTORICALS!G4*365 | H11: =HISTORICALS!H14/HISTORICALS!H4*365 | I11: =HISTORICALS!I14/HISTORICALS!I4*365 | ... K11: =HISTORICALS!K14/HISTORICALS!K4*365 | L11: =BALANCE!B5/INCOME!B4*365 | M11: =BALANCE!C5/INCOME!C4*365 | N11: =BALANCE!D5/INCOME!D4*365 | O11: =BALANCE!E5/INCOME!E4*365 | P11: =BALANCE!F5/INCOME!F4*365 | Q11: =BALANCE!G5/INCOME!G4*365 | R11: =BALANCE!H5/INCOME!H4*365
A12: Days inventory outstanding | B12: =HISTORICALS!B15/HISTORICALS!B5*365 | C12: =HISTORICALS!C15/HISTORICALS!C5*365 | D12: =HISTORICALS!D15/HISTORICALS!D5*365 | E12: =HISTORICALS!E15/HISTORICALS!E5*365 | F12: =HISTORICALS!F15/HISTORICALS!F5*365 | G12: =HISTORICALS!G15/HISTORICALS!G5*365 | H12: =HISTORICALS!H15/HISTORICALS!H5*365 | I12: =HISTORICALS!I15/HISTORICALS!I5*365 | ... K12: =HISTORICALS!K15/HISTORICALS!K5*365 | L12: =BALANCE!B6/INCOME!B5*365 | M12: =BALANCE!C6/INCOME!C5*365 | N12: =BALANCE!D6/INCOME!D5*365 | O12: =BALANCE!E6/INCOME!E5*365 | P12: =BALANCE!F6/INCOME!F5*365 | Q12: =BALANCE!G6/INCOME!G5*365 | R12: =BALANCE!H6/INCOME!H5*365
A13: Days payables outstanding | B13: =HISTORICALS!B21/HISTORICALS!B5*365 | C13: =HISTORICALS!C21/HISTORICALS!C5*365 | D13: =HISTORICALS!D21/HISTORICALS!D5*365 | E13: =HISTORICALS!E21/HISTORICALS!E5*365 | F13: =HISTORICALS!F21/HISTORICALS!F5*365 | G13: =HISTORICALS!G21/HISTORICALS!G5*365 | H13: =HISTORICALS!H21/HISTORICALS!H5*365 | I13: =HISTORICALS!I21/HISTORICALS!I5*365 | ... K13: =HISTORICALS!K21/HISTORICALS!K5*365 | L13: =BALANCE!B12/INCOME!B5*365 | M13: =BALANCE!C12/INCOME!C5*365 | N13: =BALANCE!D12/INCOME!D5*365 | O13: =BALANCE!E12/INCOME!E5*365 | P13: =BALANCE!F12/INCOME!F5*365 | Q13: =BALANCE!G12/INCOME!G5*365 | R13: =BALANCE!H12/INCOME!H5*365
A14: Cash conversion cycle (days) | B14: =B11+B12-B13 | C14: =C11+C12-C13 | D14: =D11+D12-D13 | E14: =E11+E12-E13 | F14: =F11+F12-F13 | G14: =G11+G12-G13 | H14: =H11+H12-H13 | I14: =I11+I12-I13 | ... R14: =R11+R12-R13
A15: Fixed asset turnover | B15: =HISTORICALS!B4/HISTORICALS!B17 | C15: =HISTORICALS!C4/HISTORICALS!C17 | D15: =HISTORICALS!D4/HISTORICALS!D17 | E15: =HISTORICALS!E4/HISTORICALS!E17 | F15: =HISTORICALS!F4/HISTORICALS!F17 | G15: =HISTORICALS!G4/HISTORICALS!G17 | H15: =HISTORICALS!H4/HISTORICALS!H17 | I15: =HISTORICALS!I4/HISTORICALS!I17 | ... K15: =HISTORICALS!K4/HISTORICALS!K17 | L15: =INCOME!B4/BALANCE!B8 | M15: =INCOME!C4/BALANCE!C8 | N15: =INCOME!D4/BALANCE!D8 | O15: =INCOME!E4/BALANCE!E8 | P15: =INCOME!F4/BALANCE!F8 | Q15: =INCOME!G4/BALANCE!G8 | R15: =INCOME!H4/BALANCE!H8
A16: Net debt / EBITDA | B16: =(HISTORICALS!B24-HISTORICALS!B13)/HISTORICALS!B8 | C16: =(HISTORICALS!C24-HISTORICALS!C13)/HISTORICALS!C8 | D16: =(HISTORICALS!D24-HISTORICALS!D13)/HISTORICALS!D8 | E16: =(HISTORICALS!E24-HISTORICALS!E13)/HISTORICALS!E8 | F16: =(HISTORICALS!F24-HISTORICALS!F13)/HISTORICALS!F8 | G16: =(HISTORICALS!G24-HISTORICALS!G13)/HISTORICALS!G8 | H16: =(HISTORICALS!H24-HISTORICALS!H13)/HISTORICALS!H8 | I16: =(HISTORICALS!I24-HISTORICALS!I13)/HISTORICALS!I8 | ... K16: =(HISTORICALS!K24-HISTORICALS!K13)/HISTORICALS!K8 | L16: =BALANCE!B24/INCOME!B8 | M16: =BALANCE!C24/INCOME!C8 | N16: =BALANCE!D24/INCOME!D8 | O16: =BALANCE!E24/INCOME!E8 | P16: =BALANCE!F24/INCOME!F8 | Q16: =BALANCE!G24/INCOME!G8 | R16: =BALANCE!H24/INCOME!H8
A17: EBIT / interest expense | B17: =HISTORICALS!B10/HISTORICALS!B37 | C17: =HISTORICALS!C10/HISTORICALS!C37 | D17: =HISTORICALS!D10/HISTORICALS!D37 | E17: =HISTORICALS!E10/HISTORICALS!E37 | F17: =HISTORICALS!F10/HISTORICALS!F37 | G17: =HISTORICALS!G10/HISTORICALS!G37 | H17: =HISTORICALS!H10/HISTORICALS!H37 | I17: =HISTORICALS!I10/HISTORICALS!I37 | ... K17: =HISTORICALS!K10/HISTORICALS!K37 | L17: =INCOME!B10/INCOME!B11 | M17: =INCOME!C10/INCOME!C11 | N17: =INCOME!D10/INCOME!D11 | O17: =INCOME!E10/INCOME!E11 | P17: =INCOME!F10/INCOME!F11 | Q17: =INCOME!G10/INCOME!G11 | R17: =INCOME!H10/INCOME!H11
A18: Return on capital employed | B18: =HISTORICALS!B10/(HISTORICALS!B19-HISTORICALS!B21-HISTORICALS!B22) | C18: =HISTORICALS!C10/(HISTORICALS!C19-HISTORICALS!C21-HISTORICALS!C22) | D18: =HISTORICALS!D10/(HISTORICALS!D19-HISTORICALS!D21-HISTORICALS!D22) | E18: =HISTORICALS!E10/(HISTORICALS!E19-HISTORICALS!E21-HISTORICALS!E22) | F18: =HISTORICALS!F10/(HISTORICALS!F19-HISTORICALS!F21-HISTORICALS!F22) | G18: =HISTORICALS!G10/(HISTORICALS!G19-HISTORICALS!G21-HISTORICALS!G22) | H18: =HISTORICALS!H10/(HISTORICALS!H19-HISTORICALS!H21-HISTORICALS!H22) | I18: =HISTORICALS!I10/(HISTORICALS!I19-HISTORICALS!I21-HISTORICALS!I22) | ... K18: =HISTORICALS!K10/(HISTORICALS!K19-HISTORICALS!K21-HISTORICALS!K22) | L18: =INCOME!B10/(BALANCE!B10-BALANCE!B12-BALANCE!B13) | M18: =INCOME!C10/(BALANCE!C10-BALANCE!C12-BALANCE!C13) | N18: =INCOME!D10/(BALANCE!D10-BALANCE!D12-BALANCE!D13) | O18: =INCOME!E10/(BALANCE!E10-BALANCE!E12-BALANCE!E13) | P18: =INCOME!F10/(BALANCE!F10-BALANCE!F12-BALANCE!F13) | Q18: =INCOME!G10/(BALANCE!G10-BALANCE!G12-BALANCE!G13) | R18: =INCOME!H10/(BALANCE!H10-BALANCE!H12-BALANCE!H13)
A19: Return on equity | B19: =NA() | C19: =HISTORICALS!C36/((HISTORICALS!C26+HISTORICALS!B26)/2) | D19: =HISTORICALS!D36/((HISTORICALS!D26+HISTORICALS!C26)/2) | E19: =HISTORICALS!E36/((HISTORICALS!E26+HISTORICALS!D26)/2) | F19: =HISTORICALS!F36/((HISTORICALS!F26+HISTORICALS!E26)/2) | G19: =HISTORICALS!G36/((HISTORICALS!G26+HISTORICALS!F26)/2) | H19: =HISTORICALS!H36/((HISTORICALS!H26+HISTORICALS!G26)/2) | I19: =HISTORICALS!I36/((HISTORICALS!I26+HISTORICALS!H26)/2) | J19: =HISTORICALS!J36/((HISTORICALS!J26+HISTORICALS!I26)/2) | K19: =HISTORICALS!K36/((HISTORICALS!K26+HISTORICALS!J26)/2) | L19: =INCOME!B15/DUPONT!L11 | M19: =INCOME!C15/DUPONT!M11 | N19: =INCOME!D15/DUPONT!N11 | O19: =INCOME!E15/DUPONT!O11 | P19: =INCOME!F15/DUPONT!P11 | Q19: =INCOME!G15/DUPONT!Q11 | R19: =INCOME!H15/DUPONT!R11
A20: Retention ratio | B20: =NA() | C20: =NA() | D20: =NA() | E20: =NA() | F20: =NA() | G20: =NA() | H20: =NA() | I20: =NA() | ... K20: =NA() | L20: =1-INCOME!B16/INCOME!B15 | M20: =1-INCOME!C16/INCOME!C15 | N20: =1-INCOME!D16/INCOME!D15 | O20: =1-INCOME!E16/INCOME!E15 | P20: =1-INCOME!F16/INCOME!F15 | Q20: =1-INCOME!G16/INCOME!G15 | R20: =1-INCOME!H16/INCOME!H15
A21: Sustainable growth (retention x ROE) | B21: =NA() | C21: =NA() | D21: =NA() | E21: =NA() | F21: =NA() | G21: =NA() | H21: =NA() | I21: =NA() | ... K21: =NA() | L21: =L20*L19 | M21: =M20*M19 | N21: =N20*N19 | O21: =O20*O19 | P21: =P20*P19 | Q21: =Q20*Q19 | R21: =R20*R19
A22: CFO / revenue | B22: =HISTORICALS!B38/HISTORICALS!B4 | C22: =HISTORICALS!C38/HISTORICALS!C4 | D22: =HISTORICALS!D38/HISTORICALS!D4 | E22: =HISTORICALS!E38/HISTORICALS!E4 | F22: =HISTORICALS!F38/HISTORICALS!F4 | G22: =HISTORICALS!G38/HISTORICALS!G4 | H22: =HISTORICALS!H38/HISTORICALS!H4 | I22: =HISTORICALS!I38/HISTORICALS!I4 | ... K22: =HISTORICALS!K38/HISTORICALS!K4 | L22: =CASHFLOW!B7/INCOME!B4 | M22: =CASHFLOW!C7/INCOME!C4 | N22: =CASHFLOW!D7/INCOME!D4 | O22: =CASHFLOW!E7/INCOME!E4 | P22: =CASHFLOW!F7/INCOME!F4 | Q22: =CASHFLOW!G7/INCOME!G4 | R22: =CASHFLOW!H7/INCOME!H4
A23: CFO / total assets | B23: =HISTORICALS!B38/HISTORICALS!B19 | C23: =HISTORICALS!C38/HISTORICALS!C19 | D23: =HISTORICALS!D38/HISTORICALS!D19 | E23: =HISTORICALS!E38/HISTORICALS!E19 | F23: =HISTORICALS!F38/HISTORICALS!F19 | G23: =HISTORICALS!G38/HISTORICALS!G19 | H23: =HISTORICALS!H38/HISTORICALS!H19 | I23: =HISTORICALS!I38/HISTORICALS!I19 | ... K23: =HISTORICALS!K38/HISTORICALS!K19 | L23: =CASHFLOW!B7/BALANCE!B10 | M23: =CASHFLOW!C7/BALANCE!C10 | N23: =CASHFLOW!D7/BALANCE!D10 | O23: =CASHFLOW!E7/BALANCE!E10 | P23: =CASHFLOW!F7/BALANCE!F10 | Q23: =CASHFLOW!G7/BALANCE!G10 | R23: =CASHFLOW!H7/BALANCE!H10
A24: CFO / total debt | B24: =HISTORICALS!B38/HISTORICALS!B24 | C24: =HISTORICALS!C38/HISTORICALS!C24 | D24: =HISTORICALS!D38/HISTORICALS!D24 | E24: =HISTORICALS!E38/HISTORICALS!E24 | F24: =HISTORICALS!F38/HISTORICALS!F24 | G24: =HISTORICALS!G38/HISTORICALS!G24 | H24: =HISTORICALS!H38/HISTORICALS!H24 | I24: =HISTORICALS!I38/HISTORICALS!I24 | ... K24: =HISTORICALS!K38/HISTORICALS!K24 | L24: =CASHFLOW!B7/(BALANCE!B15+BALANCE!B16) | M24: =CASHFLOW!C7/(BALANCE!C15+BALANCE!C16) | N24: =CASHFLOW!D7/(BALANCE!D15+BALANCE!D16) | O24: =CASHFLOW!E7/(BALANCE!E15+BALANCE!E16) | P24: =CASHFLOW!F7/(BALANCE!F15+BALANCE!F16) | Q24: =CASHFLOW!G7/(BALANCE!G15+BALANCE!G16) | R24: =CASHFLOW!H7/(BALANCE!H15+BALANCE!H16)
A25: Levered FCF / EBITDA | B25: =NA() | C25: =NA() | D25: =NA() | E25: =NA() | F25: =NA() | G25: =NA() | H25: =NA() | I25: =NA() | ... K25: =NA() | L25: =CASHFLOW!B21/INCOME!B8 | M25: =CASHFLOW!C21/INCOME!C8 | N25: =CASHFLOW!D21/INCOME!D8 | O25: =CASHFLOW!E21/INCOME!E8 | P25: =CASHFLOW!F21/INCOME!F8 | Q25: =CASHFLOW!G21/INCOME!G8 | R25: =CASHFLOW!H21/INCOME!H8

Sheet DUPONT
A1: DUPONT — where the return on equity actually comes from
A2: Margin, asset efficiency and leverage. Two companies with the same ROE can be entirely different businesses; this says which. Balances are averaged, so a year-end raise does not flatter the year.
A3: Component | B3: 2016 | C3: 2017 | D3: 2018 | E3: 2019 | F3: 2020 | G3: 2021 | H3: 2022 | I3: 2023 | J3: 2024 | K3: 2025 | L3: 2026 | M3: 2027 | N3: 2028 | O3: 2029 | P3: 2030 | Q3: 2031 | R3: 2032
A4: Net income | B4: =HISTORICALS!B36 | C4: =HISTORICALS!C36 | D4: =HISTORICALS!D36 | E4: =HISTORICALS!E36 | F4: =HISTORICALS!F36 | G4: =HISTORICALS!G36 | H4: =HISTORICALS!H36 | I4: =HISTORICALS!I36 | ... K4: =HISTORICALS!K36 | L4: =INCOME!B15 | M4: =INCOME!C15 | N4: =INCOME!D15 | O4: =INCOME!E15 | P4: =INCOME!F15 | Q4: =INCOME!G15 | R4: =INCOME!H15
A5: Revenue | B5: =HISTORICALS!B4 | C5: =HISTORICALS!C4 | D5: =HISTORICALS!D4 | E5: =HISTORICALS!E4 | F5: =HISTORICALS!F4 | G5: =HISTORICALS!G4 | H5: =HISTORICALS!H4 | I5: =HISTORICALS!I4 | ... K5: =HISTORICALS!K4 | L5: =INCOME!B4 | M5: =INCOME!C4 | N5: =INCOME!D4 | O5: =INCOME!E4 | P5: =INCOME!F4 | Q5: =INCOME!G4 | R5: =INCOME!H4
A6: Net profit margin (A) | B6: =B4/B5 | C6: =C4/C5 | D6: =D4/D5 | E6: =E4/E5 | F6: =F4/F5 | G6: =G4/G5 | H6: =H4/H5 | I6: =I4/I5 | ... R6: =R4/R5
A8: Average total assets | B8: =NA() | C8: =(HISTORICALS!C19+HISTORICALS!B19)/2 | D8: =(HISTORICALS!D19+HISTORICALS!C19)/2 | E8: =(HISTORICALS!E19+HISTORICALS!D19)/2 | F8: =(HISTORICALS!F19+HISTORICALS!E19)/2 | G8: =(HISTORICALS!G19+HISTORICALS!F19)/2 | H8: =(HISTORICALS!H19+HISTORICALS!G19)/2 | I8: =(HISTORICALS!I19+HISTORICALS!H19)/2 | J8: =(HISTORICALS!J19+HISTORICALS!I19)/2 | K8: =(HISTORICALS!K19+HISTORICALS!J19)/2 | L8: =(BALANCE!B10+HISTORICALS!$K$19)/2 | M8: =(BALANCE!C10+BALANCE!B10)/2 | N8: =(BALANCE!D10+BALANCE!C10)/2 | O8: =(BALANCE!E10+BALANCE!D10)/2 | P8: =(BALANCE!F10+BALANCE!E10)/2 | Q8: =(BALANCE!G10+BALANCE!F10)/2 | R8: =(BALANCE!H10+BALANCE!G10)/2
A9: Asset turnover (B) | B9: =NA() | C9: =C5/C8 | D9: =D5/D8 | E9: =E5/E8 | F9: =F5/F8 | G9: =G5/G8 | H9: =H5/H8 | I9: =I5/I8 | J9: =J5/J8 | ... R9: =R5/R8
A11: Average shareholders' equity | B11: =NA() | C11: =(HISTORICALS!C26+HISTORICALS!B26)/2 | D11: =(HISTORICALS!D26+HISTORICALS!C26)/2 | E11: =(HISTORICALS!E26+HISTORICALS!D26)/2 | F11: =(HISTORICALS!F26+HISTORICALS!E26)/2 | G11: =(HISTORICALS!G26+HISTORICALS!F26)/2 | H11: =(HISTORICALS!H26+HISTORICALS!G26)/2 | I11: =(HISTORICALS!I26+HISTORICALS!H26)/2 | J11: =(HISTORICALS!J26+HISTORICALS!I26)/2 | K11: =(HISTORICALS!K26+HISTORICALS!J26)/2 | L11: =(BALANCE!B18+HISTORICALS!$K$26)/2 | M11: =(BALANCE!C18+BALANCE!B18)/2 | N11: =(BALANCE!D18+BALANCE!C18)/2 | O11: =(BALANCE!E18+BALANCE!D18)/2 | P11: =(BALANCE!F18+BALANCE!E18)/2 | Q11: =(BALANCE!G18+BALANCE!F18)/2 | R11: =(BALANCE!H18+BALANCE!G18)/2
A12: Equity multiplier (C) | B12: =NA() | C12: =C8/C11 | D12: =D8/D11 | E12: =E8/E11 | F12: =F8/F11 | G12: =G8/G11 | H12: =H8/H11 | I12: =I8/I11 | J12: =J8/J11 | ... R12: =R8/R11
A14: Return on equity (A x B x C) | B14: =NA() | C14: =C6*C9*C12 | D14: =D6*D9*D12 | E14: =E6*E9*E12 | F14: =F6*F9*F12 | G14: =G6*G9*G12 | H14: =H6*H9*H12 | I14: =I6*I9*I12 | J14: =J6*J9*J12 | ... R14: =R6*R9*R12
A15: Return on equity (direct) | B15: =NA() | C15: =C4/C11 | D15: =D4/D11 | E15: =E4/E11 | F15: =F4/F11 | G15: =G4/G11 | H15: =H4/H11 | I15: =I4/I11 | J15: =J4/J11 | ... R15: =R4/R11
A16: Difference | B16: =NA() | C16: =C14-C15 | D16: =D14-D15 | E16: =E14-E15 | F16: =F14-F15 | G16: =G14-G15 | H16: =H14-H15 | I16: =I14-I15 | J16: =J14-J15 | ... R16: =R14-R15 | S16: Must be zero: the decomposition is an identity, so if it drifts the components are not the ones being multiplied
A18: Return on assets (A x B) | B18: =NA() | C18: =C6*C9 | D18: =D6*D9 | E18: =E6*E9 | F18: =F6*F9 | G18: =G6*G9 | H18: =H6*H9 | I18: =I6*I9 | J18: =J6*J9 | ... R18: =R6*R9

Sheet CHECKS
A1: CHECKS — live assertions, recomputed by Excel
A2: Every row must read PASS. These recompute identities independently of the cells they test.
A3: Check | B3: Result | C3: What it proves
A4: Forecast balance sheet balances every year | B4: =IF(SUMPRODUCT(MAX(ABS(BALANCE!B21:H21)))<0.01,"PASS","FAIL") | C4: Assets = liabilities + equity in every projected year. The single most important check in a three-statement model
A5: Reported balance sheet balanced every year | B5: =IF(SUMPRODUCT(MAX(ABS(HISTORICALS!B28:K28)))<0.01,"PASS","FAIL") | C5: The history was transcribed correctly
A6: Cash never falls below the minimum | B6: =IF(MIN(BALANCE!B4:H4)>=INPUTS!$B$8-0.01,"PASS","FAIL") | C6: The revolver is doing its job as the plug
A7: Closing cash ties to the cash flow statement | B7: =IF(SUMPRODUCT(MAX(ABS(CASHFLOW!B18:H18-BALANCE!B4:H4)))<0.01,"PASS","FAIL") | C7: Balance sheet cash is the cash flow statement's closing line
A8: Equity rolls forward correctly | B8: =IF(ABS(BALANCE!B18-(HISTORICALS!$K$26+INCOME!B17))<0.01,"PASS","FAIL") | C8: Opening equity + net income - dividends = closing equity
A9: PP&E rolls forward correctly | B9: =IF(ABS(BALANCE!B8-(HISTORICALS!$K$17-CASHFLOW!B8-INCOME!B9))<0.01,"PASS","FAIL") | C9: Opening PP&E + capex - depreciation = closing PP&E
A10: Cash from operations identity | B10: =IF(SUMPRODUCT(MAX(ABS(CASHFLOW!B7:H7-CASHFLOW!B4:H4-CASHFLOW!B5:H5-CASHFLOW!B6:H6)))<0.01,"PASS","FAIL") | C10: CFO = net income + D&A + change in working capital
A11: Term debt never goes negative | B11: =IF(MIN(BALANCE!B15:H15)>=-0.01,"PASS","FAIL") | C11: Scheduled repayment never exceeds the balance outstanding
A12: Interest charged on opening balances | B12: =IF(ABS(INCOME!B11-(HISTORICALS!$K$24*INPUTS!$B$5+INPUTS!$B$10*INPUTS!$B$6))<0.01,"PASS","FAIL") | C12: No circular reference: year 1 interest uses the last reported debt
A13: Revenue growth matches the input | B13: =IF(ABS(INCOME!C4/INCOME!B4-1-INPUTS!C13)<0.0001,"PASS","FAIL") | C13: The statements are actually driven by the assumptions
A14: Working capital days match the inputs | B14: =IF(ABS(BALANCE!B5/INCOME!B4*365-INPUTS!B18)<0.01,"PASS","FAIL") | C14: Receivables are genuinely driven by the DSO assumption
A15: DuPont decomposition is an identity | B15: =IF(SUMPRODUCT(MAX(ABS(DUPONT!L16:R16)))<0.000001,"PASS","FAIL") | C15: Margin x asset turnover x equity multiplier equals ROE computed directly, in every forecast year
A16: Year-1 EBITDA margin at or above the historical trough | B16: =IF(INCOME!B8/INCOME!B4>=HISTORICALS!$B$44,"PASS","REVIEW") | C16: The forecast is not starting below anything the company has lived through; REVIEW means justify it, not hide it
A18: OVERALL | B18: =IF(COUNTIF(B4:B16,"FAIL")=0,"ALL PASS","FAILURES PRESENT")
